Efinix/Trion/K5Stack10_MIDI/src/common/Serial/UartRX.v
//----------------------------------------------------------
// Clk Enable信号生成モジュール
// 
// 	2022-7-18:	pSysClk のタイミングで pTimeCke 分カウント時 Cke 出力
// 	2022-7-28:	Enable 生成タイミングをパラメータ設定とレジスタ経由から設定できるように変更
//----------------------------------------------------------
/*-----------------------------------------------------------------------------
 * Create  2023/04/15
 * Author  kouta kimura
 * -
 * UART RX module
 * 
 *-----------------------------------------------------------------------------*/
module UartRX #(
	parameter	pBaudRate 	= 31250
)(
	// UART RX
	input  iUartRX,
	// Status
	output [7:0] oRd,
	output oVd,
	// Clk Reset
    input  iRST,
    input  iCLK
);



//-----------------------------------------------------------------------------
// UART Decord
//-----------------------------------------------------------------------------
localparam lpBaudRateWidth = func_getwidth(pBaudRate);
localparam [lpBaudRateWidth-1:0] lpBaudRate = pBaudRate;
localparam [1:0]
	lpStartBit = 0,
	lpSampling = 1,
	lpStopBit  = 2;

reg  [1:0] rState;
reg  [lpBaudRateWidth-1:0] rBaudRateCnt;
reg  qBaudRateCntMaxCke;
reg  [3:0] rSampCnt;
reg  qSampCke;
reg  qRdCke;
reg  [7:0] rRd;			assign oRd = {rRd[0],rRd[1],rRd[2],rRd[3],rRd[4],rRd[5],rRd[6],rRd[7]};	// LSB から取得するので Bit Swap する
reg  rVd, qVdCke;		assign oVd = rVd;

always @(posedge iCLK)
begin
	if (iRST)
	begin
		rState	<= lpStartBit;
	end
	else
	begin
		case (rState)
			lpStartBit:	rState	<= (iUartRX) ? lpStartBit : lpSampling;
			lpSampling:	rState	<= (qSampCke) ? lpStopBit : lpSampling;
			lpStopBit: 	rState	<= (qBaudRateCntMaxCke) ? lpStartBit : lpStopBit;
			default: 	rState	<= lpStartBit;
		endcase
	end
end

always @(posedge iCLK)
begin
	if (qRdCke) rRd <= {rRd[6:0], iUartRX};	// ボーレートの速度でサンプル
	else 		rRd <=  rRd;

	if (iRST)				rVd <= 1'b0;
	else if (qVdCke)		rVd <= 1'b1;
	else 					rVd <= 1'b0;

	if (rState==lpStartBit)			rSampCnt <= 4'd0;
	else if (qBaudRateCntMaxCke)	rSampCnt <= rSampCnt + 1'b1;	// 8bit検出時にサンプリング完了信号生成
	else 							rSampCnt <= rSampCnt;

	if (rState==lpStartBit) 		rBaudRateCnt <= {lpBaudRateWidth{1'b0}};
	else if (qBaudRateCntMaxCke)	rBaudRateCnt <= {lpBaudRateWidth{1'b0}};
	else 							rBaudRateCnt <= rBaudRateCnt + 1'b1;
end

always @*
begin
	qBaudRateCntMaxCke <= (rBaudRateCnt == lpBaudRate);
	qSampCke <= (rSampCnt == 4'd8);
	qRdCke   <= &{qBaudRateCntMaxCke,rState==lpSampling};
	qVdCke   <= &{qBaudRateCntMaxCke,qSampCke};
end

//---------------------------------------------------------------------------
// msb側の1を検出しbit幅を取得する
//---------------------------------------------------------------------------
function[  7:0]	func_getwidth;
    input [31:0] iVAL;
    integer			i;

    begin
    func_getwidth = 1;
    for (i = 0; i < 32; i = i+1 )
        if (iVAL[i]) begin
            func_getwidth = i+1;
        end
    end
endfunction

endmodule

Efinix/Trion/K5Stack10_MIDI/src/common/Serial/sim/UartRX_tb.v
/*-----------------------------------------------------------------------------
 * Create  2023/04/15
 * Author  koutakimura
 * -
 * UartRX のテストベンチ
 * 
 *-----------------------------------------------------------------------------*/
module UartRX_tb;

//----------------------------------------------------------
// System Clk Generator
//----------------------------------------------------------
localparam	lpCLKCycle = 2;	// CLK サイクル

reg	rCLK = 0;
reg	rRST = 1;

always begin
    #(lpCLKCycle/2);
    rCLK = ~rCLK;
end

task reset_init;	// Reset 処理
begin
	#(lpCLKCycle * 5);
	rRST = 0;
	#(lpCLKCycle * 5);
end
endtask //


//-----------------------------------------------------------------------------
// I2S Gen
//-----------------------------------------------------------------------------
reg  [9:0] rUartRX;
wire [7:0] wRd;
wire wVd;
reg  [1:0] rCnt;

UartRX #(
	.pBaudRate(2)
) UartRX (
	.iUartRX(rUartRX[9]),
	//
	.oRd(wRd),
	.oVd(wVd),
	//
	.iRST(rRST),
	.iCLK(rCLK)
);

always @(negedge rCLK)
begin
	if (rRST) 				rCnt <= 0;
	else if (rCnt==2'd2)	rCnt <= 0;
	else 					rCnt <= rCnt + 1'b1;;

	if (rRST) 				rUartRX <= 'b1001110101;
	else if (rCnt==2'd2)	rUartRX <= {rUartRX[8:0], 1'b1};
	else 					rUartRX <= rUartRX;
end


//----------------------------------------------------------
// Simlation Start
//----------------------------------------------------------
initial begin
	$dumpfile("UartRX_tb.vcd");
	$dumpvars(0, UartRX_tb);	// 引数0:下位モジュール表示, 1:Topのみ
	reset_init();
	#(lpCLKCycle * 4800);
    $finish;
end


endmodule

Efinix/Trion/K5Stack10_MIDI/src/common/Serial/UartRX_tb.vcd
$date
	Sun Apr 16 20:59:59 2023
$end
$version
	Icarus Verilog
$end
$timescale
	1s
$end
$scope module UartRX_tb $end
$var wire 1 ! wVd $end
$var wire 8 " wRd [7:0] $end
$var reg 1 # rCLK $end
$var reg 2 $ rCnt [1:0] $end
$var reg 1 % rRST $end
$var reg 10 & rUartRX [9:0] $end
$scope module UartRX $end
$var wire 1 # iCLK $end
$var wire 1 % iRST $end
$var wire 1 ' iUartRX $end
$var wire 1 ! oVd $end
$var wire 8 ( oRd [7:0] $end
$var reg 1 ) qBaudRateCntMaxCke $end
$var reg 1 * qRdCke $end
$var reg 1 + qSampCke $end
$var reg 1 , qVdCke $end
$var reg 2 - rBaudRateCnt [1:0] $end
$var reg 8 . rRd [7:0] $end
$var reg 4 / rSampCnt [3:0] $end
$var reg 2 0 rState [1:0] $end
$var reg 1 1 rVd $end
$scope function func_getwidth $end
$var reg 32 2 iVAL [31:0] $end
$var integer 32 3 i [31:0] $end
$upscope $end
$upscope $end
$scope task reset_init $end
$upscope $end
$upscope $end
$enddefinitions $end
#0
$dumpvars
bx 3
bx 2
x1
bx 0
bx /
bx .
bx -
x,
x+
x*
x)
bx (
x'
bx &
1%
bx $
0#
bx "
x!
$end
#1
0*
b0 0
0!
01
1#
#2
1'
b1001110101 &
b0 $
0#
#3
0,
0+
0)
b0 -
b0 /
1#
#4
0#
#5
1#
#6
0#
#7
1#
#8
0#
#9
1#
#10
b1 $
0#
0%
#11
1#
#12
b10 $
0#
#13
1#
#14
0'
b11101011 &
b0 $
0#
#15
b1 0
1#
#16
b1 $
0#
#17
b1 -
1#
#18
b10 $
0#
#19
1*
1)
b10 -
1#
#20
b111010111 &
b0 $
0#
#21
0*
0)
b0xxxxxxx "
b0xxxxxxx (
b0 -
b1 /
bx0 .
1#
#22
b1 $
0#
#23
b1 -
1#
#24
b10 $
0#
#25
1*
1)
b10 -
1#
#26
1'
b1110101111 &
b0 $
0#
#27
0*
0)
b10xxxxxx "
b10xxxxxx (
b0 -
b10 /
bx01 .
1#
#28
b1 $
0#
#29
b1 -
1#
#30
b10 $
0#
#31
1*
1)
b10 -
1#
#32
b1101011111 &
b0 $
0#
#33
0*
0)
b110xxxxx "
b110xxxxx (
b0 -
b11 /
bx011 .
1#
#34
b1 $
0#
#35
b1 -
1#
#36
b10 $
0#
#37
1*
1)
b10 -
1#
#38
b1010111111 &
b0 $
0#
#39
0*
0)
b1110xxxx "
b1110xxxx (
b0 -
b100 /
bx0111 .
1#
#40
b1 $
0#
#41
b1 -
1#
#42
b10 $
0#
#43
1*
1)
b10 -
1#
#44
0'
b101111111 &
b0 $
0#
#45
0*
0)
b1110xxx "
b1110xxx (
b0 -
b101 /
bx01110 .
1#
#46
b1 $
0#
#47
b1 -
1#
#48
b10 $
0#
#49
1*
1)
b10 -
1#
#50
1'
b1011111111 &
b0 $
0#
#51
0*
0)
b101110xx "
b101110xx (
b0 -
b110 /
bx011101 .
1#
#52
b1 $
0#
#53
b1 -
1#
#54
b10 $
0#
#55
1*
1)
b10 -
1#
#56
0'
b111111111 &
b0 $
0#
#57
0*
0)
b101110x "
b101110x (
b0 -
b111 /
bx0111010 .
1#
#58
b1 $
0#
#59
b1 -
1#
#60
b10 $
0#
#61
1*
1)
b10 -
1#
#62
1'
b1111111111 &
b0 $
0#
#63
0*
1+
0)
b10101110 "
b10101110 (
b0 -
b1000 /
b1110101 .
1#
#64
b1 $
0#
#65
b10 0
b1 -
1#
#66
b10 $
0#
#67
1,
1)
b10 -
1#
#68
b0 $
0#
#69
0,
0+
0)
b0 0
b0 -
b1001 /
1!
11
1#
#70
b1 $
0#
#71
b0 /
0!
01
1#
#72
b10 $
0#
#73
1#
#74
b0 $
0#
#75
1#
#76
b1 $
0#
#77
1#
#78
b10 $
0#
#79
1#
#80
b0 $
0#
#81
1#
#82
b1 $
0#
#83
1#
#84
b10 $
0#
#85
1#
#86
b0 $
0#
#87
1#
#88
b1 $
0#
#89
1#
#90
b10 $
0#
#91
1#
#92
b0 $
0#
#93
1#
#94
b1 $
0#
#95
1#
#96
b10 $
0#
#97
1#
#98
b0 $
0#
#99
1#
#100
b1 $
0#
#101
1#
#102
b10 $
0#
#103
1#
#104
b0 $
0#
#105
1#
#106
b1 $
0#
#107
1#
#108
b10 $
0#
#109
1#
#110
b0 $
0#
#111
1#
#112
b1 $
0#
#113
1#
#114
b10 $
0#
#115
1#
#116
b0 $
0#
#117
1#
#118
b1 $
0#
#119
1#
#120
b10 $
0#
#121
1#
#122
b0 $
0#
#123
1#
#124
b1 $
0#
#125
1#
#126
b10 $
0#
#127
1#
#128
b0 $
0#
#129
1#
#130
b1 $
0#
#131
1#
#132
b10 $
0#
#133
1#
#134
b0 $
0#
#135
1#
#136
b1 $
0#
#137
1#
#138
b10 $
0#
#139
1#
#140
b0 $
0#
#141
1#
#142
b1 $
0#
#143
1#
#144
b10 $
0#
#145
1#
#146
b0 $
0#
#147
1#
#148
b1 $
0#
#149
1#
#150
b10 $
0#
#151
1#
#152
b0 $
0#
#153
1#
#154
b1 $
0#
#155
1#
#156
b10 $
0#
#157
1#
#158
b0 $
0#
#159
1#
#160
b1 $
0#
#161
1#
#162
b10 $
0#
#163
1#
#164
b0 $
0#
#165
1#
#166
b1 $
0#
#167
1#
#168
b10 $
0#
#169
1#
#170
b0 $
0#
#171
1#
#172
b1 $
0#
#173
1#
#174
b10 $
0#
#175
1#
#176
b0 $
0#
#177
1#
#178
b1 $
0#
#179
1#
#180
b10 $
0#
#181
1#
#182
b0 $
0#
#183
1#
#184
b1 $
0#
#185
1#
#186
b10 $
0#
#187
1#
#188
b0 $
0#
#189
1#
#190
b1 $
0#
#191
1#
#192
b10 $
0#
#193
1#
#194
b0 $
0#
#195
1#
#196
b1 $
0#
#197
1#
#198
b10 $
0#
#199
1#
#200
b0 $
0#
#201
1#
#202
b1 $
0#
#203
1#
#204
b10 $
0#
#205
1#
#206
b0 $
0#
#207
1#
#208
b1 $
0#
#209
1#
#210
b10 $
0#
#211
1#
#212
b0 $
0#
#213
1#
#214
b1 $
0#
#215
1#
#216
b10 $
0#
#217
1#
#218
b0 $
0#
#219
1#
#220
b1 $
0#
#221
1#
#222
b10 $
0#
#223
1#
#224
b0 $
0#
#225
1#
#226
b1 $
0#
#227
1#
#228
b10 $
0#
#229
1#
#230
b0 $
0#
#231
1#
#232
b1 $
0#
#233
1#
#234
b10 $
0#
#235
1#
#236
b0 $
0#
#237
1#
#238
b1 $
0#
#239
1#
#240
b10 $
0#
#241
1#
#242
b0 $
0#
#243
1#
#244
b1 $
0#
#245
1#
#246
b10 $
0#
#247
1#
#248
b0 $
0#
#249
1#
#250
b1 $
0#
#251
1#
#252
b10 $
0#
#253
1#
#254
b0 $
0#
#255
1#
#256
b1 $
0#
#257
1#
#258
b10 $
0#
#259
1#
#260
b0 $
0#
#261
1#
#262
b1 $
0#
#263
1#
#264
b10 $
0#
#265
1#
#266
b0 $
0#
#267
1#
#268
b1 $
0#
#269
1#
#270
b10 $
0#
#271
1#
#272
b0 $
0#
#273
1#
#274
b1 $
0#
#275
1#
#276
b10 $
0#
#277
1#
#278
b0 $
0#
#279
1#
#280
b1 $
0#
#281
1#
#282
b10 $
0#
#283
1#
#284
b0 $
0#
#285
1#
#286
b1 $
0#
#287
1#
#288
b10 $
0#
#289
1#
#290
b0 $
0#
#291
1#
#292
b1 $
0#
#293
1#
#294
b10 $
0#
#295
1#
#296
b0 $
0#
#297
1#
#298
b1 $
0#
#299
1#
#300
b10 $
0#
#301
1#
#302
b0 $
0#
#303
1#
#304
b1 $
0#
#305
1#
#306
b10 $
0#
#307
1#
#308
b0 $
0#
#309
1#
#310
b1 $
0#
#311
1#
#312
b10 $
0#
#313
1#
#314
b0 $
0#
#315
1#
#316
b1 $
0#
#317
1#
#318
b10 $
0#
#319
1#
#320
b0 $
0#
#321
1#
#322
b1 $
0#
#323
1#
#324
b10 $
0#
#325
1#
#326
b0 $
0#
#327
1#
#328
b1 $
0#
#329
1#
#330
b10 $
0#
#331
1#
#332
b0 $
0#
#333
1#
#334
b1 $
0#
#335
1#
#336
b10 $
0#
#337
1#
#338
b0 $
0#
#339
1#
#340
b1 $
0#
#341
1#
#342
b10 $
0#
#343
1#
#344
b0 $
0#
#345
1#
#346
b1 $
0#
#347
1#
#348
b10 $
0#
#349
1#
#350
b0 $
0#
#351
1#
#352
b1 $
0#
#353
1#
#354
b10 $
0#
#355
1#
#356
b0 $
0#
#357
1#
#358
b1 $
0#
#359
1#
#360
b10 $
0#
#361
1#
#362
b0 $
0#
#363
1#
#364
b1 $
0#
#365
1#
#366
b10 $
0#
#367
1#
#368
b0 $
0#
#369
1#
#370
b1 $
0#
#371
1#
#372
b10 $
0#
#373
1#
#374
b0 $
0#
#375
1#
#376
b1 $
0#
#377
1#
#378
b10 $
0#
#379
1#
#380
b0 $
0#
#381
1#
#382
b1 $
0#
#383
1#
#384
b10 $
0#
#385
1#
#386
b0 $
0#
#387
1#
#388
b1 $
0#
#389
1#
#390
b10 $
0#
#391
1#
#392
b0 $
0#
#393
1#
#394
b1 $
0#
#395
1#
#396
b10 $
0#
#397
1#
#398
b0 $
0#
#399
1#
#400
b1 $
0#
#401
1#
#402
b10 $
0#
#403
1#
#404
b0 $
0#
#405
1#
#406
b1 $
0#
#407
1#
#408
b10 $
0#
#409
1#
#410
b0 $
0#
#411
1#
#412
b1 $
0#
#413
1#
#414
b10 $
0#
#415
1#
#416
b0 $
0#
#417
1#
#418
b1 $
0#
#419
1#
#420
b10 $
0#
#421
1#
#422
b0 $
0#
#423
1#
#424
b1 $
0#
#425
1#
#426
b10 $
0#
#427
1#
#428
b0 $
0#
#429
1#
#430
b1 $
0#
#431
1#
#432
b10 $
0#
#433
1#
#434
b0 $
0#
#435
1#
#436
b1 $
0#
#437
1#
#438
b10 $
0#
#439
1#
#440
b0 $
0#
#441
1#
#442
b1 $
0#
#443
1#
#444
b10 $
0#
#445
1#
#446
b0 $
0#
#447
1#
#448
b1 $
0#
#449
1#
#450
b10 $
0#
#451
1#
#452
b0 $
0#
#453
1#
#454
b1 $
0#
#455
1#
#456
b10 $
0#
#457
1#
#458
b0 $
0#
#459
1#
#460
b1 $
0#
#461
1#
#462
b10 $
0#
#463
1#
#464
b0 $
0#
#465
1#
#466
b1 $
0#
#467
1#
#468
b10 $
0#
#469
1#
#470
b0 $
0#
#471
1#
#472
b1 $
0#
#473
1#
#474
b10 $
0#
#475
1#
#476
b0 $
0#
#477
1#
#478
b1 $
0#
#479
1#
#480
b10 $
0#
#481
1#
#482
b0 $
0#
#483
1#
#484
b1 $
0#
#485
1#
#486
b10 $
0#
#487
1#
#488
b0 $
0#
#489
1#
#490
b1 $
0#
#491
1#
#492
b10 $
0#
#493
1#
#494
b0 $
0#
#495
1#
#496
b1 $
0#
#497
1#
#498
b10 $
0#
#499
1#
#500
b0 $
0#
#501
1#
#502
b1 $
0#
#503
1#
#504
b10 $
0#
#505
1#
#506
b0 $
0#
#507
1#
#508
b1 $
0#
#509
1#
#510
b10 $
0#
#511
1#
#512
b0 $
0#
#513
1#
#514
b1 $
0#
#515
1#
#516
b10 $
0#
#517
1#
#518
b0 $
0#
#519
1#
#520
b1 $
0#
#521
1#
#522
b10 $
0#
#523
1#
#524
b0 $
0#
#525
1#
#526
b1 $
0#
#527
1#
#528
b10 $
0#
#529
1#
#530
b0 $
0#
#531
1#
#532
b1 $
0#
#533
1#
#534
b10 $
0#
#535
1#
#536
b0 $
0#
#537
1#
#538
b1 $
0#
#539
1#
#540
b10 $
0#
#541
1#
#542
b0 $
0#
#543
1#
#544
b1 $
0#
#545
1#
#546
b10 $
0#
#547
1#
#548
b0 $
0#
#549
1#
#550
b1 $
0#
#551
1#
#552
b10 $
0#
#553
1#
#554
b0 $
0#
#555
1#
#556
b1 $
0#
#557
1#
#558
b10 $
0#
#559
1#
#560
b0 $
0#
#561
1#
#562
b1 $
0#
#563
1#
#564
b10 $
0#
#565
1#
#566
b0 $
0#
#567
1#
#568
b1 $
0#
#569
1#
#570
b10 $
0#
#571
1#
#572
b0 $
0#
#573
1#
#574
b1 $
0#
#575
1#
#576
b10 $
0#
#577
1#
#578
b0 $
0#
#579
1#
#580
b1 $
0#
#581
1#
#582
b10 $
0#
#583
1#
#584
b0 $
0#
#585
1#
#586
b1 $
0#
#587
1#
#588
b10 $
0#
#589
1#
#590
b0 $
0#
#591
1#
#592
b1 $
0#
#593
1#
#594
b10 $
0#
#595
1#
#596
b0 $
0#
#597
1#
#598
b1 $
0#
#599
1#
#600
b10 $
0#
#601
1#
#602
b0 $
0#
#603
1#
#604
b1 $
0#
#605
1#
#606
b10 $
0#
#607
1#
#608
b0 $
0#
#609
1#
#610
b1 $
0#
#611
1#
#612
b10 $
0#
#613
1#
#614
b0 $
0#
#615
1#
#616
b1 $
0#
#617
1#
#618
b10 $
0#
#619
1#
#620
b0 $
0#
#621
1#
#622
b1 $
0#
#623
1#
#624
b10 $
0#
#625
1#
#626
b0 $
0#
#627
1#
#628
b1 $
0#
#629
1#
#630
b10 $
0#
#631
1#
#632
b0 $
0#
#633
1#
#634
b1 $
0#
#635
1#
#636
b10 $
0#
#637
1#
#638
b0 $
0#
#639
1#
#640
b1 $
0#
#641
1#
#642
b10 $
0#
#643
1#
#644
b0 $
0#
#645
1#
#646
b1 $
0#
#647
1#
#648
b10 $
0#
#649
1#
#650
b0 $
0#
#651
1#
#652
b1 $
0#
#653
1#
#654
b10 $
0#
#655
1#
#656
b0 $
0#
#657
1#
#658
b1 $
0#
#659
1#
#660
b10 $
0#
#661
1#
#662
b0 $
0#
#663
1#
#664
b1 $
0#
#665
1#
#666
b10 $
0#
#667
1#
#668
b0 $
0#
#669
1#
#670
b1 $
0#
#671
1#
#672
b10 $
0#
#673
1#
#674
b0 $
0#
#675
1#
#676
b1 $
0#
#677
1#
#678
b10 $
0#
#679
1#
#680
b0 $
0#
#681
1#
#682
b1 $
0#
#683
1#
#684
b10 $
0#
#685
1#
#686
b0 $
0#
#687
1#
#688
b1 $
0#
#689
1#
#690
b10 $
0#
#691
1#
#692
b0 $
0#
#693
1#
#694
b1 $
0#
#695
1#
#696
b10 $
0#
#697
1#
#698
b0 $
0#
#699
1#
#700
b1 $
0#
#701
1#
#702
b10 $
0#
#703
1#
#704
b0 $
0#
#705
1#
#706
b1 $
0#
#707
1#
#708
b10 $
0#
#709
1#
#710
b0 $
0#
#711
1#
#712
b1 $
0#
#713
1#
#714
b10 $
0#
#715
1#
#716
b0 $
0#
#717
1#
#718
b1 $
0#
#719
1#
#720
b10 $
0#
#721
1#
#722
b0 $
0#
#723
1#
#724
b1 $
0#
#725
1#
#726
b10 $
0#
#727
1#
#728
b0 $
0#
#729
1#
#730
b1 $
0#
#731
1#
#732
b10 $
0#
#733
1#
#734
b0 $
0#
#735
1#
#736
b1 $
0#
#737
1#
#738
b10 $
0#
#739
1#
#740
b0 $
0#
#741
1#
#742
b1 $
0#
#743
1#
#744
b10 $
0#
#745
1#
#746
b0 $
0#
#747
1#
#748
b1 $
0#
#749
1#
#750
b10 $
0#
#751
1#
#752
b0 $
0#
#753
1#
#754
b1 $
0#
#755
1#
#756
b10 $
0#
#757
1#
#758
b0 $
0#
#759
1#
#760
b1 $
0#
#761
1#
#762
b10 $
0#
#763
1#
#764
b0 $
0#
#765
1#
#766
b1 $
0#
#767
1#
#768
b10 $
0#
#769
1#
#770
b0 $
0#
#771
1#
#772
b1 $
0#
#773
1#
#774
b10 $
0#
#775
1#
#776
b0 $
0#
#777
1#
#778
b1 $
0#
#779
1#
#780
b10 $
0#
#781
1#
#782
b0 $
0#
#783
1#
#784
b1 $
0#
#785
1#
#786
b10 $
0#
#787
1#
#788
b0 $
0#
#789
1#
#790
b1 $
0#
#791
1#
#792
b10 $
0#
#793
1#
#794
b0 $
0#
#795
1#
#796
b1 $
0#
#797
1#
#798
b10 $
0#
#799
1#
#800
b0 $
0#
#801
1#
#802
b1 $
0#
#803
1#
#804
b10 $
0#
#805
1#
#806
b0 $
0#
#807
1#
#808
b1 $
0#
#809
1#
#810
b10 $
0#
#811
1#
#812
b0 $
0#
#813
1#
#814
b1 $
0#
#815
1#
#816
b10 $
0#
#817
1#
#818
b0 $
0#
#819
1#
#820
b1 $
0#
#821
1#
#822
b10 $
0#
#823
1#
#824
b0 $
0#
#825
1#
#826
b1 $
0#
#827
1#
#828
b10 $
0#
#829
1#
#830
b0 $
0#
#831
1#
#832
b1 $
0#
#833
1#
#834
b10 $
0#
#835
1#
#836
b0 $
0#
#837
1#
#838
b1 $
0#
#839
1#
#840
b10 $
0#
#841
1#
#842
b0 $
0#
#843
1#
#844
b1 $
0#
#845
1#
#846
b10 $
0#
#847
1#
#848
b0 $
0#
#849
1#
#850
b1 $
0#
#851
1#
#852
b10 $
0#
#853
1#
#854
b0 $
0#
#855
1#
#856
b1 $
0#
#857
1#
#858
b10 $
0#
#859
1#
#860
b0 $
0#
#861
1#
#862
b1 $
0#
#863
1#
#864
b10 $
0#
#865
1#
#866
b0 $
0#
#867
1#
#868
b1 $
0#
#869
1#
#870
b10 $
0#
#871
1#
#872
b0 $
0#
#873
1#
#874
b1 $
0#
#875
1#
#876
b10 $
0#
#877
1#
#878
b0 $
0#
#879
1#
#880
b1 $
0#
#881
1#
#882
b10 $
0#
#883
1#
#884
b0 $
0#
#885
1#
#886
b1 $
0#
#887
1#
#888
b10 $
0#
#889
1#
#890
b0 $
0#
#891
1#
#892
b1 $
0#
#893
1#
#894
b10 $
0#
#895
1#
#896
b0 $
0#
#897
1#
#898
b1 $
0#
#899
1#
#900
b10 $
0#
#901
1#
#902
b0 $
0#
#903
1#
#904
b1 $
0#
#905
1#
#906
b10 $
0#
#907
1#
#908
b0 $
0#
#909
1#
#910
b1 $
0#
#911
1#
#912
b10 $
0#
#913
1#
#914
b0 $
0#
#915
1#
#916
b1 $
0#
#917
1#
#918
b10 $
0#
#919
1#
#920
b0 $
0#
#921
1#
#922
b1 $
0#
#923
1#
#924
b10 $
0#
#925
1#
#926
b0 $
0#
#927
1#
#928
b1 $
0#
#929
1#
#930
b10 $
0#
#931
1#
#932
b0 $
0#
#933
1#
#934
b1 $
0#
#935
1#
#936
b10 $
0#
#937
1#
#938
b0 $
0#
#939
1#
#940
b1 $
0#
#941
1#
#942
b10 $
0#
#943
1#
#944
b0 $
0#
#945
1#
#946
b1 $
0#
#947
1#
#948
b10 $
0#
#949
1#
#950
b0 $
0#
#951
1#
#952
b1 $
0#
#953
1#
#954
b10 $
0#
#955
1#
#956
b0 $
0#
#957
1#
#958
b1 $
0#
#959
1#
#960
b10 $
0#
#961
1#
#962
b0 $
0#
#963
1#
#964
b1 $
0#
#965
1#
#966
b10 $
0#
#967
1#
#968
b0 $
0#
#969
1#
#970
b1 $
0#
#971
1#
#972
b10 $
0#
#973
1#
#974
b0 $
0#
#975
1#
#976
b1 $
0#
#977
1#
#978
b10 $
0#
#979
1#
#980
b0 $
0#
#981
1#
#982
b1 $
0#
#983
1#
#984
b10 $
0#
#985
1#
#986
b0 $
0#
#987
1#
#988
b1 $
0#
#989
1#
#990
b10 $
0#
#991
1#
#992
b0 $
0#
#993
1#
#994
b1 $
0#
#995
1#
#996
b10 $
0#
#997
1#
#998
b0 $
0#
#999
1#
#1000
b1 $
0#
#1001
1#
#1002
b10 $
0#
#1003
1#
#1004
b0 $
0#
#1005
1#
#1006
b1 $
0#
#1007
1#
#1008
b10 $
0#
#1009
1#
#1010
b0 $
0#
#1011
1#
#1012
b1 $
0#
#1013
1#
#1014
b10 $
0#
#1015
1#
#1016
b0 $
0#
#1017
1#
#1018
b1 $
0#
#1019
1#
#1020
b10 $
0#
#1021
1#
#1022
b0 $
0#
#1023
1#
#1024
b1 $
0#
#1025
1#
#1026
b10 $
0#
#1027
1#
#1028
b0 $
0#
#1029
1#
#1030
b1 $
0#
#1031
1#
#1032
b10 $
0#
#1033
1#
#1034
b0 $
0#
#1035
1#
#1036
b1 $
0#
#1037
1#
#1038
b10 $
0#
#1039
1#
#1040
b0 $
0#
#1041
1#
#1042
b1 $
0#
#1043
1#
#1044
b10 $
0#
#1045
1#
#1046
b0 $
0#
#1047
1#
#1048
b1 $
0#
#1049
1#
#1050
b10 $
0#
#1051
1#
#1052
b0 $
0#
#1053
1#
#1054
b1 $
0#
#1055
1#
#1056
b10 $
0#
#1057
1#
#1058
b0 $
0#
#1059
1#
#1060
b1 $
0#
#1061
1#
#1062
b10 $
0#
#1063
1#
#1064
b0 $
0#
#1065
1#
#1066
b1 $
0#
#1067
1#
#1068
b10 $
0#
#1069
1#
#1070
b0 $
0#
#1071
1#
#1072
b1 $
0#
#1073
1#
#1074
b10 $
0#
#1075
1#
#1076
b0 $
0#
#1077
1#
#1078
b1 $
0#
#1079
1#
#1080
b10 $
0#
#1081
1#
#1082
b0 $
0#
#1083
1#
#1084
b1 $
0#
#1085
1#
#1086
b10 $
0#
#1087
1#
#1088
b0 $
0#
#1089
1#
#1090
b1 $
0#
#1091
1#
#1092
b10 $
0#
#1093
1#
#1094
b0 $
0#
#1095
1#
#1096
b1 $
0#
#1097
1#
#1098
b10 $
0#
#1099
1#
#1100
b0 $
0#
#1101
1#
#1102
b1 $
0#
#1103
1#
#1104
b10 $
0#
#1105
1#
#1106
b0 $
0#
#1107
1#
#1108
b1 $
0#
#1109
1#
#1110
b10 $
0#
#1111
1#
#1112
b0 $
0#
#1113
1#
#1114
b1 $
0#
#1115
1#
#1116
b10 $
0#
#1117
1#
#1118
b0 $
0#
#1119
1#
#1120
b1 $
0#
#1121
1#
#1122
b10 $
0#
#1123
1#
#1124
b0 $
0#
#1125
1#
#1126
b1 $
0#
#1127
1#
#1128
b10 $
0#
#1129
1#
#1130
b0 $
0#
#1131
1#
#1132
b1 $
0#
#1133
1#
#1134
b10 $
0#
#1135
1#
#1136
b0 $
0#
#1137
1#
#1138
b1 $
0#
#1139
1#
#1140
b10 $
0#
#1141
1#
#1142
b0 $
0#
#1143
1#
#1144
b1 $
0#
#1145
1#
#1146
b10 $
0#
#1147
1#
#1148
b0 $
0#
#1149
1#
#1150
b1 $
0#
#1151
1#
#1152
b10 $
0#
#1153
1#
#1154
b0 $
0#
#1155
1#
#1156
b1 $
0#
#1157
1#
#1158
b10 $
0#
#1159
1#
#1160
b0 $
0#
#1161
1#
#1162
b1 $
0#
#1163
1#
#1164
b10 $
0#
#1165
1#
#1166
b0 $
0#
#1167
1#
#1168
b1 $
0#
#1169
1#
#1170
b10 $
0#
#1171
1#
#1172
b0 $
0#
#1173
1#
#1174
b1 $
0#
#1175
1#
#1176
b10 $
0#
#1177
1#
#1178
b0 $
0#
#1179
1#
#1180
b1 $
0#
#1181
1#
#1182
b10 $
0#
#1183
1#
#1184
b0 $
0#
#1185
1#
#1186
b1 $
0#
#1187
1#
#1188
b10 $
0#
#1189
1#
#1190
b0 $
0#
#1191
1#
#1192
b1 $
0#
#1193
1#
#1194
b10 $
0#
#1195
1#
#1196
b0 $
0#
#1197
1#
#1198
b1 $
0#
#1199
1#
#1200
b10 $
0#
#1201
1#
#1202
b0 $
0#
#1203
1#
#1204
b1 $
0#
#1205
1#
#1206
b10 $
0#
#1207
1#
#1208
b0 $
0#
#1209
1#
#1210
b1 $
0#
#1211
1#
#1212
b10 $
0#
#1213
1#
#1214
b0 $
0#
#1215
1#
#1216
b1 $
0#
#1217
1#
#1218
b10 $
0#
#1219
1#
#1220
b0 $
0#
#1221
1#
#1222
b1 $
0#
#1223
1#
#1224
b10 $
0#
#1225
1#
#1226
b0 $
0#
#1227
1#
#1228
b1 $
0#
#1229
1#
#1230
b10 $
0#
#1231
1#
#1232
b0 $
0#
#1233
1#
#1234
b1 $
0#
#1235
1#
#1236
b10 $
0#
#1237
1#
#1238
b0 $
0#
#1239
1#
#1240
b1 $
0#
#1241
1#
#1242
b10 $
0#
#1243
1#
#1244
b0 $
0#
#1245
1#
#1246
b1 $
0#
#1247
1#
#1248
b10 $
0#
#1249
1#
#1250
b0 $
0#
#1251
1#
#1252
b1 $
0#
#1253
1#
#1254
b10 $
0#
#1255
1#
#1256
b0 $
0#
#1257
1#
#1258
b1 $
0#
#1259
1#
#1260
b10 $
0#
#1261
1#
#1262
b0 $
0#
#1263
1#
#1264
b1 $
0#
#1265
1#
#1266
b10 $
0#
#1267
1#
#1268
b0 $
0#
#1269
1#
#1270
b1 $
0#
#1271
1#
#1272
b10 $
0#
#1273
1#
#1274
b0 $
0#
#1275
1#
#1276
b1 $
0#
#1277
1#
#1278
b10 $
0#
#1279
1#
#1280
b0 $
0#
#1281
1#
#1282
b1 $
0#
#1283
1#
#1284
b10 $
0#
#1285
1#
#1286
b0 $
0#
#1287
1#
#1288
b1 $
0#
#1289
1#
#1290
b10 $
0#
#1291
1#
#1292
b0 $
0#
#1293
1#
#1294
b1 $
0#
#1295
1#
#1296
b10 $
0#
#1297
1#
