Efinix/Trion/K5Stack10_MIDI/src/SynthesizerBlock/I2SSignalGen.v
//----------------------------------------------------------
// Create 2023/4/9
// Author koutakimura
// -
// V1.0 : I2S 信号生成 module
// 
//----------------------------------------------------------
module I2SSignalGen (
	// I2S Output Ctrl
	output oI2S_MCLK,
	output oI2S_BCLK,
	output oI2S_LRCLK,	// Low "LCLK", High "RCLK"
	output oI2S_SDATA,
	// Control and Data
	input  [31:0] iAudioData,
	output oAudioDataRdy,
    // CLK Reset
	input  iMRST,
    input  iSRST,
	input  iMCLK,
    input  iSCLK
);


/**-----------------------------------------------------------------------------
I2S I/F Signals Generator
PCM5102Aの仕様上、32bit SDATA は [0][31][30][29]...[1]の順番で送信しなければならない
各信号の生成に使用する MCLK COUNT はSDRでカウント値をインクリメントしていることに注意

 *-----------------------------------------------------------------------------*/
localparam lpMclkCntWidth = 8;
genvar x;
reg  [1:0] rMclkBCnt;	// BCLK 生成カウンタ  = 3.072MHz
reg  [lpMclkCntWidth-1:0] rMclkLRCnt;	// LRCLK 生成カウンタ = 48KHz
reg  rBclk, qBclkCke;
reg  rLRclk, qLRclkCke;
reg  [31:0] rSdata, qSdata;
reg  qSdataSftCke;
// control
reg  rRdy, qRdyCke;

always @(negedge iMCLK)
begin

	if (iMRST) 			rMclkBCnt <= 2'd0;
	else if	(qBclkCke)	rMclkBCnt <= 2'd0;
	else 				rMclkBCnt <= rMclkBCnt + 1'b1;

	if (iMRST) 			rBclk <= 1'b0;
	else if	(qBclkCke)	rBclk <= ~rBclk;
	else 				rBclk <=  rBclk;

	if (iMRST) 			rMclkLRCnt <= {lpMclkCntWidth{1'b0}};
	else 				rMclkLRCnt <= rMclkLRCnt + 1'b1;

	if (iMRST) 			rLRclk <= 1'b0;
	else if	(qLRclkCke)	rLRclk <= ~rLRclk;
	else 				rLRclk <=  rLRclk;

	if (qLRclkCke)			rSdata <=  qSdata;
	else if	(qSdataSftCke)	rSdata <= {rSdata[30:0],1'b0};
	else 					rSdata <=  rSdata;

	if (iMRST) 			rRdy <= 1'b0;	//Right音源出力のときに、次の音源データを読みこみ
	else if	(qRdyCke)	rRdy <= 1'b1;	// Ready Valid のタイミング入れ違い対策として
	else 				rRdy <= 1'b0;	// Rdy は 1ショットパルスの動作とする
end

always @*
begin
	qBclkCke  <= rMclkBCnt == 2'd3;
	qLRclkCke <= rMclkLRCnt == {lpMclkCntWidth{1'b1}};
	qSdataSftCke <= qBclkCke & rBclk;	// BCLK のたち下がりエッジで SDATAシフト
	qRdyCke   <= qLRclkCke & (~rLRclk);
end

assign oI2S_MCLK	= iMCLK;
assign oI2S_BCLK	= rBclk;
assign oI2S_LRCLK	= rLRclk;
assign oI2S_SDATA	= rSdata[31];
assign oAudioDataRdy= rRdy;


//-----------------------------------------------------------------------------
// PCM5102 I2S仕様に則り、ビット位置を変更
//-----------------------------------------------------------------------------
always @*
begin
	qSdata[0] <= iAudioData[30];
	qSdata[1] <= iAudioData[29];
	qSdata[2] <= iAudioData[28];
	qSdata[3] <= iAudioData[27];
	qSdata[4] <= iAudioData[26];
	qSdata[5] <= iAudioData[25];
	qSdata[6] <= iAudioData[24];
	qSdata[7] <= iAudioData[23];
	qSdata[8] <= iAudioData[22];
	qSdata[9] <= iAudioData[21];
	qSdata[10] <= iAudioData[20];
	qSdata[11] <= iAudioData[19];
	qSdata[12] <= iAudioData[18];
	qSdata[13] <= iAudioData[17];
	qSdata[14] <= iAudioData[16];
	qSdata[15] <= iAudioData[15];
	qSdata[16] <= iAudioData[14];
	qSdata[17] <= iAudioData[13];
	qSdata[18] <= iAudioData[12];
	qSdata[19] <= iAudioData[11];
	qSdata[20] <= iAudioData[10];
	qSdata[21] <= iAudioData[9];
	qSdata[22] <= iAudioData[8];
	qSdata[23] <= iAudioData[7];
	qSdata[24] <= iAudioData[6];
	qSdata[25] <= iAudioData[5];
	qSdata[26] <= iAudioData[4];
	qSdata[27] <= iAudioData[3];
	qSdata[28] <= iAudioData[2];
	qSdata[29] <= iAudioData[1];
	qSdata[30] <= iAudioData[0];
	qSdata[31] <= iAudioData[31];
end

endmodule

Efinix/Trion/K5Stack10_MIDI/src/SynthesizerBlock/sim/I2SSignalGen_tb.v
/*-----------------------------------------------------------------------------
 * Create  2023/04/15
 * Author  koutakimura
 * -
 * I2SSignalGen のテストベンチ
 * 
 *-----------------------------------------------------------------------------*/
module I2SSignalGen_tb;

//----------------------------------------------------------
// System Clk Generator
//----------------------------------------------------------
localparam	lpMCLKCycle = 2;	// CLK サイクル

reg	rMCLK = 0;
reg	rMRST = 1;

always begin
    #(lpMCLKCycle/2);
    rMCLK = ~rMCLK;
end

task reset_init;	// Reset 処理
begin
	#(lpMCLKCycle * 5);
	rMRST = 0;
	#(lpMCLKCycle * 5);
end
endtask //


//-----------------------------------------------------------------------------
// I2S Gen
//-----------------------------------------------------------------------------
wire wI2S_MCLK, wI2S_BCLK, wI2S_LRCLK, wI2S_SDATA;
reg  [31:0] rAudioData;
wire wAudioDataRdy;

I2SSignalGen I2SSignalGen(
	.oI2S_MCLK(wI2S_MCLK),		.oI2S_BCLK(wI2S_BCLK),
	.oI2S_LRCLK(wI2S_LRCLK),	.oI2S_SDATA(wI2S_SDATA),
	//
	.iAudioData(rAudioData),	.oAudioDataRdy(wAudioDataRdy),
	//
	.iMRST(rMRST),	.iSRST(),
	.iMCLK(rMCLK),	.iSCLK()
);

always @(posedge rMCLK)
begin
	if (rMRST) 				rAudioData <= 32'd0;
	else if (wAudioDataRdy)	rAudioData <= rAudioData + 1'b1;
	else 					rAudioData <= rAudioData;
end


//----------------------------------------------------------
// Simlation Start
//----------------------------------------------------------
initial begin
	$dumpfile("I2SSignalGen_tb.vcd");
	$dumpvars(0, I2SSignalGen_tb);	// 引数0:下位モジュール表示, 1:Topのみ
	reset_init();
	#(lpMCLKCycle * 4800);
    $finish;
end


endmodule

Efinix/Trion/K5Stack10_MIDI/src/SynthesizerBlock/I2SSignalGen_tb.vcd
$date
	Sun Apr 16 15:27:26 2023
$end
$version
	Icarus Verilog
$end
$timescale
	1s
$end
$scope module I2SSignalGen_tb $end
$var wire 1 ! wI2S_SDATA $end
$var wire 1 " wI2S_MCLK $end
$var wire 1 # wI2S_LRCLK $end
$var wire 1 $ wI2S_BCLK $end
$var wire 1 % wAudioDataRdy $end
$var reg 32 & rAudioData [31:0] $end
$var reg 1 ' rMCLK $end
$var reg 1 ( rMRST $end
$scope module I2SSignalGen $end
$var wire 32 ) iAudioData [31:0] $end
$var wire 1 ' iMCLK $end
$var wire 1 ( iMRST $end
$var wire 1 * iSCLK $end
$var wire 1 + iSRST $end
$var wire 1 % oAudioDataRdy $end
$var wire 1 $ oI2S_BCLK $end
$var wire 1 # oI2S_LRCLK $end
$var wire 1 " oI2S_MCLK $end
$var wire 1 ! oI2S_SDATA $end
$var reg 1 , qBclkCke $end
$var reg 1 - qLRclkCke $end
$var reg 1 . qRdyCke $end
$var reg 32 / qSdata [31:0] $end
$var reg 1 0 qSdataSftCke $end
$var reg 1 1 rBclk $end
$var reg 1 2 rLRclk $end
$var reg 2 3 rMclkBCnt [1:0] $end
$var reg 8 4 rMclkLRCnt [7:0] $end
$var reg 1 5 rRdy $end
$var reg 32 6 rSdata [31:0] $end
$upscope $end
$scope task reset_init $end
$upscope $end
$upscope $end
$enddefinitions $end
#0
$dumpvars
bx 6
05
b0 4
b0 3
02
01
00
bx /
0.
0-
0,
z+
z*
bx )
1(
0'
bx &
0%
0$
0#
0"
x!
$end
#1
b0 /
b0 &
b0 )
1"
1'
#2
0"
0'
#3
1"
1'
#4
0"
0'
#5
1"
1'
#6
0"
0'
#7
1"
1'
#8
0"
0'
#9
1"
1'
#10
b1 4
b1 3
0"
0'
0(
#11
1"
1'
#12
b10 4
b10 3
0"
0'
#13
1"
1'
#14
1,
b11 4
b11 3
0"
0'
#15
1"
1'
#16
00
0,
b100 4
1$
11
b0 3
0"
0'
#17
1"
1'
#18
b101 4
b1 3
0"
0'
#19
1"
1'
#20
b110 4
b10 3
0"
0'
#21
1"
1'
#22
10
1,
b111 4
b11 3
0"
0'
#23
1"
1'
#24
00
0,
bx0 6
b1000 4
0$
01
b0 3
0"
0'
#25
1"
1'
#26
b1001 4
b1 3
0"
0'
#27
1"
1'
#28
b1010 4
b10 3
0"
0'
#29
1"
1'
#30
1,
b1011 4
b11 3
0"
0'
#31
1"
1'
#32
00
0,
b1100 4
1$
11
b0 3
0"
0'
#33
1"
1'
#34
b1101 4
b1 3
0"
0'
#35
1"
1'
#36
b1110 4
b10 3
0"
0'
#37
1"
1'
#38
10
1,
b1111 4
b11 3
0"
0'
#39
1"
1'
#40
00
0,
bx00 6
b10000 4
0$
01
b0 3
0"
0'
#41
1"
1'
#42
b10001 4
b1 3
0"
0'
#43
1"
1'
#44
b10010 4
b10 3
0"
0'
#45
1"
1'
#46
1,
b10011 4
b11 3
0"
0'
#47
1"
1'
#48
00
0,
b10100 4
1$
11
b0 3
0"
0'
#49
1"
1'
#50
b10101 4
b1 3
0"
0'
#51
1"
1'
#52
b10110 4
b10 3
0"
0'
#53
1"
1'
#54
10
1,
b10111 4
b11 3
0"
0'
#55
1"
1'
#56
00
0,
bx000 6
b11000 4
0$
01
b0 3
0"
0'
#57
1"
1'
#58
b11001 4
b1 3
0"
0'
#59
1"
1'
#60
b11010 4
b10 3
0"
0'
#61
1"
1'
#62
1,
b11011 4
b11 3
0"
0'
#63
1"
1'
#64
00
0,
b11100 4
1$
11
b0 3
0"
0'
#65
1"
1'
#66
b11101 4
b1 3
0"
0'
#67
1"
1'
#68
b11110 4
b10 3
0"
0'
#69
1"
1'
#70
10
1,
b11111 4
b11 3
0"
0'
#71
1"
1'
#72
00
0,
bx0000 6
b100000 4
0$
01
b0 3
0"
0'
#73
1"
1'
#74
b100001 4
b1 3
0"
0'
#75
1"
1'
#76
b100010 4
b10 3
0"
0'
#77
1"
1'
#78
1,
b100011 4
b11 3
0"
0'
#79
1"
1'
#80
00
0,
b100100 4
1$
11
b0 3
0"
0'
#81
1"
1'
#82
b100101 4
b1 3
0"
0'
#83
1"
1'
#84
b100110 4
b10 3
0"
0'
#85
1"
1'
#86
10
1,
b100111 4
b11 3
0"
0'
#87
1"
1'
#88
00
0,
bx00000 6
b101000 4
0$
01
b0 3
0"
0'
#89
1"
1'
#90
b101001 4
b1 3
0"
0'
#91
1"
1'
#92
b101010 4
b10 3
0"
0'
#93
1"
1'
#94
1,
b101011 4
b11 3
0"
0'
#95
1"
1'
#96
00
0,
b101100 4
1$
11
b0 3
0"
0'
#97
1"
1'
#98
b101101 4
b1 3
0"
0'
#99
1"
1'
#100
b101110 4
b10 3
0"
0'
#101
1"
1'
#102
10
1,
b101111 4
b11 3
0"
0'
#103
1"
1'
#104
00
0,
bx000000 6
b110000 4
0$
01
b0 3
0"
0'
#105
1"
1'
#106
b110001 4
b1 3
0"
0'
#107
1"
1'
#108
b110010 4
b10 3
0"
0'
#109
1"
1'
#110
1,
b110011 4
b11 3
0"
0'
#111
1"
1'
#112
00
0,
b110100 4
1$
11
b0 3
0"
0'
#113
1"
1'
#114
b110101 4
b1 3
0"
0'
#115
1"
1'
#116
b110110 4
b10 3
0"
0'
#117
1"
1'
#118
10
1,
b110111 4
b11 3
0"
0'
#119
1"
1'
#120
00
0,
bx0000000 6
b111000 4
0$
01
b0 3
0"
0'
#121
1"
1'
#122
b111001 4
b1 3
0"
0'
#123
1"
1'
#124
b111010 4
b10 3
0"
0'
#125
1"
1'
#126
1,
b111011 4
b11 3
0"
0'
#127
1"
1'
#128
00
0,
b111100 4
1$
11
b0 3
0"
0'
#129
1"
1'
#130
b111101 4
b1 3
0"
0'
#131
1"
1'
#132
b111110 4
b10 3
0"
0'
#133
1"
1'
#134
10
1,
b111111 4
b11 3
0"
0'
#135
1"
1'
#136
00
0,
bx00000000 6
b1000000 4
0$
01
b0 3
0"
0'
#137
1"
1'
#138
b1000001 4
b1 3
0"
0'
#139
1"
1'
#140
b1000010 4
b10 3
0"
0'
#141
1"
1'
#142
1,
b1000011 4
b11 3
0"
0'
#143
1"
1'
#144
00
0,
b1000100 4
1$
11
b0 3
0"
0'
#145
1"
1'
#146
b1000101 4
b1 3
0"
0'
#147
1"
1'
#148
b1000110 4
b10 3
0"
0'
#149
1"
1'
#150
10
1,
b1000111 4
b11 3
0"
0'
#151
1"
1'
#152
00
0,
bx000000000 6
b1001000 4
0$
01
b0 3
0"
0'
#153
1"
1'
#154
b1001001 4
b1 3
0"
0'
#155
1"
1'
#156
b1001010 4
b10 3
0"
0'
#157
1"
1'
#158
1,
b1001011 4
b11 3
0"
0'
#159
1"
1'
#160
00
0,
b1001100 4
1$
11
b0 3
0"
0'
#161
1"
1'
#162
b1001101 4
b1 3
0"
0'
#163
1"
1'
#164
b1001110 4
b10 3
0"
0'
#165
1"
1'
#166
10
1,
b1001111 4
b11 3
0"
0'
#167
1"
1'
#168
00
0,
bx0000000000 6
b1010000 4
0$
01
b0 3
0"
0'
#169
1"
1'
#170
b1010001 4
b1 3
0"
0'
#171
1"
1'
#172
b1010010 4
b10 3
0"
0'
#173
1"
1'
#174
1,
b1010011 4
b11 3
0"
0'
#175
1"
1'
#176
00
0,
b1010100 4
1$
11
b0 3
0"
0'
#177
1"
1'
#178
b1010101 4
b1 3
0"
0'
#179
1"
1'
#180
b1010110 4
b10 3
0"
0'
#181
1"
1'
#182
10
1,
b1010111 4
b11 3
0"
0'
#183
1"
1'
#184
00
0,
bx00000000000 6
b1011000 4
0$
01
b0 3
0"
0'
#185
1"
1'
#186
b1011001 4
b1 3
0"
0'
#187
1"
1'
#188
b1011010 4
b10 3
0"
0'
#189
1"
1'
#190
1,
b1011011 4
b11 3
0"
0'
#191
1"
1'
#192
00
0,
b1011100 4
1$
11
b0 3
0"
0'
#193
1"
1'
#194
b1011101 4
b1 3
0"
0'
#195
1"
1'
#196
b1011110 4
b10 3
0"
0'
#197
1"
1'
#198
10
1,
b1011111 4
b11 3
0"
0'
#199
1"
1'
#200
00
0,
bx000000000000 6
b1100000 4
0$
01
b0 3
0"
0'
#201
1"
1'
#202
b1100001 4
b1 3
0"
0'
#203
1"
1'
#204
b1100010 4
b10 3
0"
0'
#205
1"
1'
#206
1,
b1100011 4
b11 3
0"
0'
#207
1"
1'
#208
00
0,
b1100100 4
1$
11
b0 3
0"
0'
#209
1"
1'
#210
b1100101 4
b1 3
0"
0'
#211
1"
1'
#212
b1100110 4
b10 3
0"
0'
#213
1"
1'
#214
10
1,
b1100111 4
b11 3
0"
0'
#215
1"
1'
#216
00
0,
bx0000000000000 6
b1101000 4
0$
01
b0 3
0"
0'
#217
1"
1'
#218
b1101001 4
b1 3
0"
0'
#219
1"
1'
#220
b1101010 4
b10 3
0"
0'
#221
1"
1'
#222
1,
b1101011 4
b11 3
0"
0'
#223
1"
1'
#224
00
0,
b1101100 4
1$
11
b0 3
0"
0'
#225
1"
1'
#226
b1101101 4
b1 3
0"
0'
#227
1"
1'
#228
b1101110 4
b10 3
0"
0'
#229
1"
1'
#230
10
1,
b1101111 4
b11 3
0"
0'
#231
1"
1'
#232
00
0,
bx00000000000000 6
b1110000 4
0$
01
b0 3
0"
0'
#233
1"
1'
#234
b1110001 4
b1 3
0"
0'
#235
1"
1'
#236
b1110010 4
b10 3
0"
0'
#237
1"
1'
#238
1,
b1110011 4
b11 3
0"
0'
#239
1"
1'
#240
00
0,
b1110100 4
1$
11
b0 3
0"
0'
#241
1"
1'
#242
b1110101 4
b1 3
0"
0'
#243
1"
1'
#244
b1110110 4
b10 3
0"
0'
#245
1"
1'
#246
10
1,
b1110111 4
b11 3
0"
0'
#247
1"
1'
#248
00
0,
bx000000000000000 6
b1111000 4
0$
01
b0 3
0"
0'
#249
1"
1'
#250
b1111001 4
b1 3
0"
0'
#251
1"
1'
#252
b1111010 4
b10 3
0"
0'
#253
1"
1'
#254
1,
b1111011 4
b11 3
0"
0'
#255
1"
1'
#256
00
0,
b1111100 4
1$
11
b0 3
0"
0'
#257
1"
1'
#258
b1111101 4
b1 3
0"
0'
#259
1"
1'
#260
b1111110 4
b10 3
0"
0'
#261
1"
1'
#262
10
1,
b1111111 4
b11 3
0"
0'
#263
1"
1'
#264
00
0,
bx0000000000000000 6
b10000000 4
0$
01
b0 3
0"
0'
#265
1"
1'
#266
b10000001 4
b1 3
0"
0'
#267
1"
1'
#268
b10000010 4
b10 3
0"
0'
#269
1"
1'
#270
1,
b10000011 4
b11 3
0"
0'
#271
1"
1'
#272
00
0,
b10000100 4
1$
11
b0 3
0"
0'
#273
1"
1'
#274
b10000101 4
b1 3
0"
0'
#275
1"
1'
#276
b10000110 4
b10 3
0"
0'
#277
1"
1'
#278
10
1,
b10000111 4
b11 3
0"
0'
#279
1"
1'
#280
00
0,
bx00000000000000000 6
b10001000 4
0$
01
b0 3
0"
0'
#281
1"
1'
#282
b10001001 4
b1 3
0"
0'
#283
1"
1'
#284
b10001010 4
b10 3
0"
0'
#285
1"
1'
#286
1,
b10001011 4
b11 3
0"
0'
#287
1"
1'
#288
00
0,
b10001100 4
1$
11
b0 3
0"
0'
#289
1"
1'
#290
b10001101 4
b1 3
0"
0'
#291
1"
1'
#292
b10001110 4
b10 3
0"
0'
#293
1"
1'
#294
10
1,
b10001111 4
b11 3
0"
0'
#295
1"
1'
#296
00
0,
bx000000000000000000 6
b10010000 4
0$
01
b0 3
0"
0'
#297
1"
1'
#298
b10010001 4
b1 3
0"
0'
#299
1"
1'
#300
b10010010 4
b10 3
0"
0'
#301
1"
1'
#302
1,
b10010011 4
b11 3
0"
0'
#303
1"
1'
#304
00
0,
b10010100 4
1$
11
b0 3
0"
0'
#305
1"
1'
#306
b10010101 4
b1 3
0"
0'
#307
1"
1'
#308
b10010110 4
b10 3
0"
0'
#309
1"
1'
#310
10
1,
b10010111 4
b11 3
0"
0'
#311
1"
1'
#312
00
0,
bx0000000000000000000 6
b10011000 4
0$
01
b0 3
0"
0'
#313
1"
1'
#314
b10011001 4
b1 3
0"
0'
#315
1"
1'
#316
b10011010 4
b10 3
0"
0'
#317
1"
1'
#318
1,
b10011011 4
b11 3
0"
0'
#319
1"
1'
#320
00
0,
b10011100 4
1$
11
b0 3
0"
0'
#321
1"
1'
#322
b10011101 4
b1 3
0"
0'
#323
1"
1'
#324
b10011110 4
b10 3
0"
0'
#325
1"
1'
#326
10
1,
b10011111 4
b11 3
0"
0'
#327
1"
1'
#328
00
0,
bx00000000000000000000 6
b10100000 4
0$
01
b0 3
0"
0'
#329
1"
1'
#330
b10100001 4
b1 3
0"
0'
#331
1"
1'
#332
b10100010 4
b10 3
0"
0'
#333
1"
1'
#334
1,
b10100011 4
b11 3
0"
0'
#335
1"
1'
#336
00
0,
b10100100 4
1$
11
b0 3
0"
0'
#337
1"
1'
#338
b10100101 4
b1 3
0"
0'
#339
1"
1'
#340
b10100110 4
b10 3
0"
0'
#341
1"
1'
#342
10
1,
b10100111 4
b11 3
0"
0'
#343
1"
1'
#344
00
0,
bx000000000000000000000 6
b10101000 4
0$
01
b0 3
0"
0'
#345
1"
1'
#346
b10101001 4
b1 3
0"
0'
#347
1"
1'
#348
b10101010 4
b10 3
0"
0'
#349
1"
1'
#350
1,
b10101011 4
b11 3
0"
0'
#351
1"
1'
#352
00
0,
b10101100 4
1$
11
b0 3
0"
0'
#353
1"
1'
#354
b10101101 4
b1 3
0"
0'
#355
1"
1'
#356
b10101110 4
b10 3
0"
0'
#357
1"
1'
#358
10
1,
b10101111 4
b11 3
0"
0'
#359
1"
1'
#360
00
0,
bx0000000000000000000000 6
b10110000 4
0$
01
b0 3
0"
0'
#361
1"
1'
#362
b10110001 4
b1 3
0"
0'
#363
1"
1'
#364
b10110010 4
b10 3
0"
0'
#365
1"
1'
#366
1,
b10110011 4
b11 3
0"
0'
#367
1"
1'
#368
00
0,
b10110100 4
1$
11
b0 3
0"
0'
#369
1"
1'
#370
b10110101 4
b1 3
0"
0'
#371
1"
1'
#372
b10110110 4
b10 3
0"
0'
#373
1"
1'
#374
10
1,
b10110111 4
b11 3
0"
0'
#375
1"
1'
#376
00
0,
bx00000000000000000000000 6
b10111000 4
0$
01
b0 3
0"
0'
#377
1"
1'
#378
b10111001 4
b1 3
0"
0'
#379
1"
1'
#380
b10111010 4
b10 3
0"
0'
#381
1"
1'
#382
1,
b10111011 4
b11 3
0"
0'
#383
1"
1'
#384
00
0,
b10111100 4
1$
11
b0 3
0"
0'
#385
1"
1'
#386
b10111101 4
b1 3
0"
0'
#387
1"
1'
#388
b10111110 4
b10 3
0"
0'
#389
1"
1'
#390
10
1,
b10111111 4
b11 3
0"
0'
#391
1"
1'
#392
00
0,
bx000000000000000000000000 6
b11000000 4
0$
01
b0 3
0"
0'
#393
1"
1'
#394
b11000001 4
b1 3
0"
0'
#395
1"
1'
#396
b11000010 4
b10 3
0"
0'
#397
1"
1'
#398
1,
b11000011 4
b11 3
0"
0'
#399
1"
1'
#400
00
0,
b11000100 4
1$
11
b0 3
0"
0'
#401
1"
1'
#402
b11000101 4
b1 3
0"
0'
#403
1"
1'
#404
b11000110 4
b10 3
0"
0'
#405
1"
1'
#406
10
1,
b11000111 4
b11 3
0"
0'
#407
1"
1'
#408
00
0,
bx0000000000000000000000000 6
b11001000 4
0$
01
b0 3
0"
0'
#409
1"
1'
#410
b11001001 4
b1 3
0"
0'
#411
1"
1'
#412
b11001010 4
b10 3
0"
0'
#413
1"
1'
#414
1,
b11001011 4
b11 3
0"
0'
#415
1"
1'
#416
00
0,
b11001100 4
1$
11
b0 3
0"
0'
#417
1"
1'
#418
b11001101 4
b1 3
0"
0'
#419
1"
1'
#420
b11001110 4
b10 3
0"
0'
#421
1"
1'
#422
10
1,
b11001111 4
b11 3
0"
0'
#423
1"
1'
#424
00
0,
bx00000000000000000000000000 6
b11010000 4
0$
01
b0 3
0"
0'
#425
1"
1'
#426
b11010001 4
b1 3
0"
0'
#427
1"
1'
#428
b11010010 4
b10 3
0"
0'
#429
1"
1'
#430
1,
b11010011 4
b11 3
0"
0'
#431
1"
1'
#432
00
0,
b11010100 4
1$
11
b0 3
0"
0'
#433
1"
1'
#434
b11010101 4
b1 3
0"
0'
#435
1"
1'
#436
b11010110 4
b10 3
0"
0'
#437
1"
1'
#438
10
1,
b11010111 4
b11 3
0"
0'
#439
1"
1'
#440
00
0,
bx000000000000000000000000000 6
b11011000 4
0$
01
b0 3
0"
0'
#441
1"
1'
#442
b11011001 4
b1 3
0"
0'
#443
1"
1'
#444
b11011010 4
b10 3
0"
0'
#445
1"
1'
#446
1,
b11011011 4
b11 3
0"
0'
#447
1"
1'
#448
00
0,
b11011100 4
1$
11
b0 3
0"
0'
#449
1"
1'
#450
b11011101 4
b1 3
0"
0'
#451
1"
1'
#452
b11011110 4
b10 3
0"
0'
#453
1"
1'
#454
10
1,
b11011111 4
b11 3
0"
0'
#455
1"
1'
#456
00
0,
bx0000000000000000000000000000 6
b11100000 4
0$
01
b0 3
0"
0'
#457
1"
1'
#458
b11100001 4
b1 3
0"
0'
#459
1"
1'
#460
b11100010 4
b10 3
0"
0'
#461
1"
1'
#462
1,
b11100011 4
b11 3
0"
0'
#463
1"
1'
#464
00
0,
b11100100 4
1$
11
b0 3
0"
0'
#465
1"
1'
#466
b11100101 4
b1 3
0"
0'
#467
1"
1'
#468
b11100110 4
b10 3
0"
0'
#469
1"
1'
#470
10
1,
b11100111 4
b11 3
0"
0'
#471
1"
1'
#472
00
0,
bx00000000000000000000000000000 6
b11101000 4
0$
01
b0 3
0"
0'
#473
1"
1'
#474
b11101001 4
b1 3
0"
0'
#475
1"
1'
#476
b11101010 4
b10 3
0"
0'
#477
1"
1'
#478
1,
b11101011 4
b11 3
0"
0'
#479
1"
1'
#480
00
0,
b11101100 4
1$
11
b0 3
0"
0'
#481
1"
1'
#482
b11101101 4
b1 3
0"
0'
#483
1"
1'
#484
b11101110 4
b10 3
0"
0'
#485
1"
1'
#486
10
1,
b11101111 4
b11 3
0"
0'
#487
1"
1'
#488
00
0,
bx000000000000000000000000000000 6
b11110000 4
0$
01
b0 3
0"
0'
#489
1"
1'
#490
b11110001 4
b1 3
0"
0'
#491
1"
1'
#492
b11110010 4
b10 3
0"
0'
#493
1"
1'
#494
1,
b11110011 4
b11 3
0"
0'
#495
1"
1'
#496
00
0,
b11110100 4
1$
11
b0 3
0"
0'
#497
1"
1'
#498
b11110101 4
b1 3
0"
0'
#499
1"
1'
#500
b11110110 4
b10 3
0"
0'
#501
1"
1'
#502
10
1,
b11110111 4
b11 3
0"
0'
#503
1"
1'
#504
00
0,
bx0000000000000000000000000000000 6
b11111000 4
0$
01
b0 3
0"
0'
#505
1"
1'
#506
b11111001 4
b1 3
0"
0'
#507
1"
1'
#508
b11111010 4
b10 3
0"
0'
#509
1"
1'
#510
1,
b11111011 4
b11 3
0"
0'
#511
1"
1'
#512
00
0,
b11111100 4
1$
11
b0 3
0"
0'
#513
1"
1'
#514
b11111101 4
b1 3
0"
0'
#515
1"
1'
#516
b11111110 4
b10 3
0"
0'
#517
1"
1'
#518
1.
10
1-
1,
b11111111 4
b11 3
0"
0'
#519
1"
1'
#520
0.
00
0-
0,
0!
1%
15
b0 6
1#
12
b0 4
0$
01
b0 3
0"
0'
#521
b1000000000000000000000000000000 /
b1 &
b1 )
1"
1'
#522
0%
05
b1 4
b1 3
0"
0'
#523
1"
1'
#524
b10 4
b10 3
0"
0'
#525
1"
1'
#526
1,
b11 4
b11 3
0"
0'
#527
1"
1'
#528
00
0,
b100 4
1$
11
b0 3
0"
0'
#529
1"
1'
#530
b101 4
b1 3
0"
0'
#531
1"
1'
#532
b110 4
b10 3
0"
0'
#533
1"
1'
#534
10
1,
b111 4
b11 3
0"
0'
#535
1"
1'
#536
00
0,
b1000 4
0$
01
b0 3
0"
0'
#537
1"
1'
#538
b1001 4
b1 3
0"
0'
#539
1"
1'
#540
b1010 4
b10 3
0"
0'
#541
1"
1'
#542
1,
b1011 4
b11 3
0"
0'
#543
1"
1'
#544
00
0,
b1100 4
1$
11
b0 3
0"
0'
#545
1"
1'
#546
b1101 4
b1 3
0"
0'
#547
1"
1'
#548
b1110 4
b10 3
0"
0'
#549
1"
1'
#550
10
1,
b1111 4
b11 3
0"
0'
#551
1"
1'
#552
00
0,
b10000 4
0$
01
b0 3
0"
0'
#553
1"
1'
#554
b10001 4
b1 3
0"
0'
#555
1"
1'
#556
b10010 4
b10 3
0"
0'
#557
1"
1'
#558
1,
b10011 4
b11 3
0"
0'
#559
1"
1'
#560
00
0,
b10100 4
1$
11
b0 3
0"
0'
#561
1"
1'
#562
b10101 4
b1 3
0"
0'
#563
1"
1'
#564
b10110 4
b10 3
0"
0'
#565
1"
1'
#566
10
1,
b10111 4
b11 3
0"
0'
#567
1"
1'
#568
00
0,
b11000 4
0$
01
b0 3
0"
0'
#569
1"
1'
#570
b11001 4
b1 3
0"
0'
#571
1"
1'
#572
b11010 4
b10 3
0"
0'
#573
1"
1'
#574
1,
b11011 4
b11 3
0"
0'
#575
1"
1'
#576
00
0,
b11100 4
1$
11
b0 3
0"
0'
#577
1"
1'
#578
b11101 4
b1 3
0"
0'
#579
1"
1'
#580
b11110 4
b10 3
0"
0'
#581
1"
1'
#582
10
1,
b11111 4
b11 3
0"
0'
#583
1"
1'
#584
00
0,
b100000 4
0$
01
b0 3
0"
0'
#585
1"
1'
#586
b100001 4
b1 3
0"
0'
#587
1"
1'
#588
b100010 4
b10 3
0"
0'
#589
1"
1'
#590
1,
b100011 4
b11 3
0"
0'
#591
1"
1'
#592
00
0,
b100100 4
1$
11
b0 3
0"
0'
#593
1"
1'
#594
b100101 4
b1 3
0"
0'
#595
1"
1'
#596
b100110 4
b10 3
0"
0'
#597
1"
1'
#598
10
1,
b100111 4
b11 3
0"
0'
#599
1"
1'
#600
00
0,
b101000 4
0$
01
b0 3
0"
0'
#601
1"
1'
#602
b101001 4
b1 3
0"
0'
#603
1"
1'
#604
b101010 4
b10 3
0"
0'
#605
1"
1'
#606
1,
b101011 4
b11 3
0"
0'
#607
1"
1'
#608
00
0,
b101100 4
1$
11
b0 3
0"
0'
#609
1"
1'
#610
b101101 4
b1 3
0"
0'
#611
1"
1'
#612
b101110 4
b10 3
0"
0'
#613
1"
1'
#614
10
1,
b101111 4
b11 3
0"
0'
#615
1"
1'
#616
00
0,
b110000 4
0$
01
b0 3
0"
0'
#617
1"
1'
#618
b110001 4
b1 3
0"
0'
#619
1"
1'
#620
b110010 4
b10 3
0"
0'
#621
1"
1'
#622
1,
b110011 4
b11 3
0"
0'
#623
1"
1'
#624
00
0,
b110100 4
1$
11
b0 3
0"
0'
#625
1"
1'
#626
b110101 4
b1 3
0"
0'
#627
1"
1'
#628
b110110 4
b10 3
0"
0'
#629
1"
1'
#630
10
1,
b110111 4
b11 3
0"
0'
#631
1"
1'
#632
00
0,
b111000 4
0$
01
b0 3
0"
0'
#633
1"
1'
#634
b111001 4
b1 3
0"
0'
#635
1"
1'
#636
b111010 4
b10 3
0"
0'
#637
1"
1'
#638
1,
b111011 4
b11 3
0"
0'
#639
1"
1'
#640
00
0,
b111100 4
1$
11
b0 3
0"
0'
#641
1"
1'
#642
b111101 4
b1 3
0"
0'
#643
1"
1'
#644
b111110 4
b10 3
0"
0'
#645
1"
1'
#646
10
1,
b111111 4
b11 3
0"
0'
#647
1"
1'
#648
00
0,
b1000000 4
0$
01
b0 3
0"
0'
#649
1"
1'
#650
b1000001 4
b1 3
0"
0'
#651
1"
1'
#652
b1000010 4
b10 3
0"
0'
#653
1"
1'
#654
1,
b1000011 4
b11 3
0"
0'
#655
1"
1'
#656
00
0,
b1000100 4
1$
11
b0 3
0"
0'
#657
1"
1'
