Efinix/Titanium/MemoryTest/Ti180_FMB_R1W1_k256m32_230125/src/ddr_reset_sequencer.v
/////////////////////////////////////////////////////////////////////////////
//
// Copyright (C) 2013-2019 Efinix Inc. All rights reserved.
//
// Description:
//
// Efinix soft logic DDR system reset controller
//
// The Trion DDR controller block, (instantiated in the Interface Designer),
// has three input pins for reset control.  (when I2C calibration not enabled)
//
//     Master Reset (active low)
//     Sequencer Reset (active high)
//     Sequencer Start (active high)
//
// This Verilog module generates outputs that can directly
// connect to these pins, given a single reset signal and a clock.
//
// The module also generates a "done" status signal, to inform user system
// when reset + DDR-reinitialization is completed, and read/write operations
// to the DDR AXI interfaces may resume.  The user should define
// FREQ parameter to correspond to frequency of their clock signal.
//
// NOTE #1:  This reset sequencer resets and re-initializes both the DDR
//           interface of the Trion device, as well as the DDR module(s)
//           themselves.
//
// NOTE #2:  The user is not expected to pulse reset upon device configuration
//           and initial entry to user mode.  During the configuration process
//           DDR reset and initialization will be triggered automatically.  This
//           soft logic reset is only required if the user needs to reset
//           the DDR system again while maintaining the Trion device in user mode.
//
// Language:  Verilog 2001
//
// ------------------------------------------------------------------------------
// REVISION:
//  $Snapshot: $
//  $Id:$
//
// History:
// 1.0 Initial Release. 
/////////////////////////////////////////////////////////////////////////////////
module ddr_reset_sequencer #(
parameter	pStartCntBitWidth	= 8
)(
input 		iRST,					// main user DDR reset, active High
input 		iCLK,					// user clock
input 		iddr_cfg_done,			// DDR_CFG_DONE
/* Connect these three signals to DDR reset interface */
output 		o_ddr_axi_rstn,			// Master Reset
output 		o_ddr_cfg_seq_rst,		// Sequencer Reset
output 		o_ddr_cfg_seq_start,	// Sequencer Start
output 		o_ddr_init_done			// Done status
);



//-----------------------------------------------------------------------------
// CFG Aequenser RESET, START
//-----------------------------------------------------------------------------
localparam 
	lpIdol 	= 2'd0,
	lpReset = 2'd1,
	lpStart = 2'd2,
	lpDone 	= 2'd3;

reg r_ddr_axi_rstn;							assign o_ddr_axi_rstn 		= r_ddr_axi_rstn;
reg r_ddr_cfg_seq_rst;						assign o_ddr_cfg_seq_rst 	= r_ddr_cfg_seq_rst;
reg r_ddr_cfg_seq_start;					assign o_ddr_cfg_seq_start 	= r_ddr_cfg_seq_start;
reg r_ddr_init_done;						assign o_ddr_init_done 		= r_ddr_init_done;
//
reg [1:0] rs;
reg [pStartCntBitWidth-1:0] rSeqCnt;
reg rSeqMaxCke;

initial
begin
	r_ddr_axi_rstn		<= 1'b0;
	r_ddr_cfg_seq_rst	<= 1'b1;
	r_ddr_cfg_seq_start	<= 1'b0;
end

always @(posedge iCLK)
begin
	if (iRST)
	begin
		rs      			<= lpIdol;
		rSeqCnt 			<= {pStartCntBitWidth{1'b0}};
		r_ddr_axi_rstn		<= 1'b0;
		r_ddr_cfg_seq_rst	<= 1'b1;
		r_ddr_cfg_seq_start	<= 1'b0;
		r_ddr_init_done		<= 1'b1;
	end
	else
	begin
		case ( rs )
			lpIdol:
			begin
				rs      			<= (rSeqMaxCke) ? lpReset : lpIdol;
				rSeqCnt 			<= (rSeqMaxCke) ? {pStartCntBitWidth{1'b0}} : rSeqCnt + 1'b1;
				r_ddr_axi_rstn		<= 1'b0;
				r_ddr_cfg_seq_rst	<= 1'b1;
				r_ddr_cfg_seq_start	<= 1'b0;
				r_ddr_init_done		<= 1'b1;
			end

			lpReset:
			begin
				rs 					<= (rSeqMaxCke) ? lpStart : lpReset;
				rSeqCnt 			<= (rSeqMaxCke) ? {pStartCntBitWidth{1'b0}} : rSeqCnt + 1'b1;
				r_ddr_axi_rstn		<= 1'b0;
				r_ddr_cfg_seq_rst	<= 1'b1;
				r_ddr_cfg_seq_start	<= 1'b0;
				r_ddr_init_done		<= 1'b1;
			end

			lpStart:
			begin
				rs 					<= (rSeqMaxCke) ? lpDone : lpStart;
				rSeqCnt 			<= (rSeqMaxCke) ? {pStartCntBitWidth{1'b0}} : rSeqCnt + 1'b1;
				r_ddr_axi_rstn		<= 1'b0;
				r_ddr_cfg_seq_rst	<= 1'b0;
				r_ddr_cfg_seq_start	<= 1'b0;
				r_ddr_init_done		<= 1'b1;
			end

			lpDone:
			begin
				rs 					<= rs;
				rSeqCnt 			<= rSeqCnt;
				r_ddr_axi_rstn		<= iddr_cfg_done;
				r_ddr_cfg_seq_rst	<= 1'b0;
				r_ddr_cfg_seq_start	<= 1'b1;
				r_ddr_init_done		<= iddr_cfg_done;
			end

			default:
			begin
				rs      			<= lpIdol;
				rSeqCnt 			<= {pStartCntBitWidth{1'b0}};
				r_ddr_axi_rstn		<= 1'b0;
				r_ddr_cfg_seq_rst	<= 1'b1;
				r_ddr_cfg_seq_start	<= 1'b0;
				r_ddr_init_done		<= 1'b0;
			end
		endcase
	end
end

always @*
begin
	rSeqMaxCke <= (rSeqCnt == {pStartCntBitWidth{1'b1}});
end
endmodule

Efinix/Titanium/MemoryTest/Ti180_FMB_R1W1_k256m32_230125/src/ddr_reset_sequencer_tb.v
/////////////////////////////////////////////////////////////////////////////
//
// Copyright (C) 2013-2019 Efinix Inc. All rights reserved.
//
// Description:
//
// Efinix soft logic DDR system reset controller
//
// The Trion DDR controller block, (instantiated in the Interface Designer),
// has three input pins for reset control.  (when I2C calibration not enabled)
//
//     Master Reset (active low)
//     Sequencer Reset (active high)
//     Sequencer Start (active high)
//
// This Verilog module generates outputs that can directly
// connect to these pins, given a single reset signal and a clock.
//
// The module also generates a "done" status signal, to inform user system
// when reset + DDR-reinitialization is completed, and read/write operations
// to the DDR AXI interfaces may resume.  The user should define
// FREQ parameter to correspond to frequency of their clock signal.
//
// NOTE #1:  This reset sequencer resets and re-initializes both the DDR
//           interface of the Trion device, as well as the DDR module(s)
//           themselves.
//
// NOTE #2:  The user is not expected to pulse reset upon device configuration
//           and initial entry to user mode.  During the configuration process
//           DDR reset and initialization will be triggered automatically.  This
//           soft logic reset is only required if the user needs to reset
//           the DDR system again while maintaining the Trion device in user mode.
//
// Language:  Verilog 2001
//
// ------------------------------------------------------------------------------
// REVISION:
//  $Snapshot: $
//  $Id:$
//
// History:
// 1.0 Initial Release. 
/////////////////////////////////////////////////////////////////////////////////

`timescale 1ns/1ps

module ddr_reset_sequencer_tb;

localparam lpCycle = 2;

reg rRST = 1'b1;
reg rCLK = 1'b0;

always
begin
	#(lpCycle/2);
	rCLK = ~rCLK;
end

//-----------------------------------------------------------------------------
// 
//-----------------------------------------------------------------------------
wire w_ddr_axi_rstn;
wire w_ddr_cfg_seq_rst;
wire w_ddr_cfg_seq_start;
wire w_ddr_init_done;

ddr_reset_sequencer #(
	.pStartCntBitWidth(3)
) ddr_reset_sequencer (
	.iRST(rRST),
	.iCLK(rCLK),
	.iddr_cfg_done(1'b1),
	.o_ddr_axi_rstn(w_ddr_axi_rstn),
	.o_ddr_cfg_seq_rst(w_ddr_cfg_seq_rst),
	.o_ddr_cfg_seq_start(w_ddr_cfg_seq_start),
	.o_ddr_init_done(w_ddr_init_done)
);


initial
begin
	$dumpfile("ddr_reset_sequencer_tb.vcd");
	$dumpvars(0, ddr_reset_sequencer_tb);	// 引数0:下位モジュール表示, 1:Topのみ
	rRST = 1'b1;
	#(lpCycle*16);
	rRST = 1'b0;
	#(lpCycle*100);
	$finish;
end

endmodule

Efinix/Titanium/MemoryTest/Ti180_FMB_R1W1_k256m32_230125/ddr_reset_sequencer_tb.vcd
$date
	Sun Jan 29 21:49:59 2023
$end
$version
	Icarus Verilog
$end
$timescale
	1ps
$end
$scope module ddr_reset_sequencer_tb $end
$var wire 1 ! w_ddr_init_done $end
$var wire 1 " w_ddr_cfg_seq_start $end
$var wire 1 # w_ddr_cfg_seq_rst $end
$var wire 1 $ w_ddr_axi_rstn $end
$var reg 1 % rCLK $end
$var reg 1 & rRST $end
$scope module ddr_reset_sequencer $end
$var wire 1 % iCLK $end
$var wire 1 & iRST $end
$var wire 1 ' iddr_cfg_done $end
$var wire 1 $ o_ddr_axi_rstn $end
$var wire 1 # o_ddr_cfg_seq_rst $end
$var wire 1 " o_ddr_cfg_seq_start $end
$var wire 1 ! o_ddr_init_done $end
$var reg 3 ( rSeqCnt [2:0] $end
$var reg 1 ) rSeqMaxCke $end
$var reg 1 * r_ddr_axi_rstn $end
$var reg 1 + r_ddr_cfg_seq_rst $end
$var reg 1 , r_ddr_cfg_seq_start $end
$var reg 1 - r_ddr_init_done $end
$var reg 2 . rs [1:0] $end
$upscope $end
$upscope $end
$enddefinitions $end
#0
$dumpvars
bx .
x-
0,
1+
0*
x)
bx (
1'
1&
0%
0$
1#
0"
x!
$end
#1000
0)
1!
1-
b0 (
b0 .
1%
#2000
0%
#3000
1%
#4000
0%
#5000
1%
#6000
0%
#7000
1%
#8000
0%
#9000
1%
#10000
0%
#11000
1%
#12000
0%
#13000
1%
#14000
0%
#15000
1%
#16000
0%
#17000
1%
#18000
0%
#19000
1%
#20000
0%
#21000
1%
#22000
0%
#23000
1%
#24000
0%
#25000
1%
#26000
0%
#27000
1%
#28000
0%
#29000
1%
#30000
0%
#31000
1%
#32000
0%
0&
#33000
b1 (
1%
#34000
0%
#35000
b10 (
1%
#36000
0%
#37000
b11 (
1%
#38000
0%
#39000
b100 (
1%
#40000
0%
#41000
b101 (
1%
#42000
0%
#43000
b110 (
1%
#44000
0%
#45000
1)
b111 (
1%
#46000
0%
#47000
0)
b0 (
b1 .
1%
#48000
0%
#49000
b1 (
1%
#50000
0%
#51000
b10 (
1%
#52000
0%
#53000
b11 (
1%
#54000
0%
#55000
b100 (
1%
#56000
0%
#57000
b101 (
1%
#58000
0%
#59000
b110 (
1%
#60000
0%
#61000
1)
b111 (
1%
#62000
0%
#63000
0)
b0 (
b10 .
1%
#64000
0%
#65000
0#
0+
b1 (
1%
#66000
0%
#67000
b10 (
1%
#68000
0%
#69000
b11 (
1%
#70000
0%
#71000
b100 (
1%
#72000
0%
#73000
b101 (
1%
#74000
0%
#75000
b110 (
1%
#76000
0%
#77000
1)
b111 (
1%
#78000
0%
#79000
0)
b0 (
b11 .
1%
#80000
0%
#81000
1"
1,
1$
1*
1%
