Efinix/Trion/K5Stack10_MIDI/src/common/pulse/PulseGenerator.v
//----------------------------------------------------------
// Pulse信号生成モジュール
// 
// 2022/7/21
// 指定タイミングで Pulse 信号を出力
//----------------------------------------------------------
module PulseGenerator #(
    parameter 		pSysClk  	= 25000000, // 分周クロックの値を指定
    parameter [7:0]	pTimeCke 	= 8'd1,     // Enable 出力の時間指定
	parameter [0:0] pStartPulse = 1'b1		// 起動時の Pulse の High/Low 指定
)(
    output  oPulse,
    input   iRST,
    input   iCLK
);


//----------------------------------------------------------
// reg Bit Length
//----------------------------------------------------------
localparam 						lpCtuCNTBits= fBitWidth(pSysClk);
localparam [lpCtuCNTBits-1:0] 	lpSysCnt 	= pSysClk-1'b1;
localparam [lpCtuCNTBits-1:0] 	lpRstCnt 	= 0;


//----------------------------------------------------------
// Cke Counter
//----------------------------------------------------------
reg [lpCtuCNTBits-1:0] rTmpCount;
reg qCke;

always @( posedge iCLK )
begin
    if (iRST)    rTmpCount <= lpRstCnt;
    else if (qCke)  rTmpCount <= lpRstCnt;
    else            rTmpCount <= rTmpCount + 1'b1;
end

always @*
begin
    qCke = rTmpCount == lpSysCnt;
end

//----------------------------------------------------------
// 指定時間カウント時 Cke 出力
//----------------------------------------------------------
reg [7:0] rTimeCkeCnt;
reg qTimeCke;

always @( posedge iCLK )
begin
    if (iRST)        rTimeCkeCnt <= 8'd0;
    else if (qTimeCke)  rTimeCkeCnt <= 8'd0;
    else if (qCke)      rTimeCkeCnt <= rTimeCkeCnt + 1'b1;
    else                rTimeCkeCnt <= rTimeCkeCnt;
end

always @*
begin
    qTimeCke <= pTimeCke == rTimeCkeCnt;
end

//----------------------------------------------------------
// Ckeの立ち上がりタイミング で Pulse をトグルさせ出力
//----------------------------------------------------------
reg  rPulse;			assign oPulse = rPulse;

always @(posedge iCLK)
begin
	if (iRST) 		rPulse <= pStartPulse;
	else if (qTimeCke)	rPulse <= ~rPulse;
	else 				rPulse <= rPulse;
end


//----------------------------------------------------------
// msb側の1を検出しbit幅を取得する
//----------------------------------------------------------
function[  7:0]	fBitWidth;
    input [31:0] iVAL;
    integer			i;

    begin
    fBitWidth = 1;
    for (i = 0; i < 32; i = i+1 )
        if (iVAL[i]) begin
            fBitWidth = i+1;
        end
    end
endfunction

endmodule

Efinix/Trion/K5Stack10_MIDI/src/common/fifo/DualPortBramTrion.v
/*-----------------------------------------------------------------------------
 * Create  2023/05/05
 * Author  kouta kimura
 * -
 * Dual Port BlockRam Trion version
 * 
 *-----------------------------------------------------------------------------*/
module DualPortBramTrion #(
    parameter 	pBuffDepth 		= 256,    // FIFO BRAMのサイズ指定
    parameter 	pBitWidth  		= 32,     // bitサイズ
    parameter 	pAddrWidth 		= 16,     // addr size
	parameter	pFifoBlockRam	= "yes"
)(
    input   [pBitWidth-1:0]    iWd,    // write data
    input   [pAddrWidth-1:0]   iWa,    // write addr
    input                      iWe,    // write enable
    output  [pBitWidth-1:0]    oRd,    // read data
    input   [pAddrWidth-1:0]   iRa,     // read address
    input                      iCLK
);

(* ram_style = "block" *) reg [pBitWidth-1:0] bram [0:pBuffDepth-1];
reg [pBitWidth-1:0] rRd;		assign oRd = rRd;

always @(posedge iCLK)
begin
	if (iWe)
	begin
		bram[iWa] <= iWd;
	end

	rRd <= bram[iRa];
end


// generate
// 	if (pFifoBlockRam == "yes")
// 	begin
// 		reg [pBitWidth-1:0] rd;     assign oRD = rd;
// 		// assign oRD = fifo[iRA];

// 		// rwポート
// 		always @(posedge iCLK)
// 		begin
// 			if (iWE) fifo[iWA] <= iWD;
// 			rd <= fifo[iRA];
// 		end
// 	end
// 	else
// 	begin
// 		assign oRD = fifo[iRA];

// 		// rwポート
// 		always @(posedge iCLK)
// 		begin
// 			if (iWE) fifo[iWA] <= iWD;
// 		end
// 	end
// endgenerate

endmodule

Efinix/Trion/K5Stack10_MIDI/src/common/fifo/SyncFifoController.v
/*-----------------------------------------------------------------------------
 * Create  2023/05/05
 * Author  koutakimura
 * -
 * 非同期リセット付き単相同期クロックFIFOコントローラ module
 * 
 *-----------------------------------------------------------------------------*/
module SyncFifoController #(
    parameter 	pFifoDepth        	= 16,		// FIFO BRAMのサイズ指定
    parameter 	pFifoBitWidth     	= 8,		// bitサイズ
	parameter	pFifoBlockRam		= "yes"		// yes BRAM, no reg
)(
    input   [pFifoBitWidth-1:0] iWd,        // write data
    input                       iWe,        // write enable 有効データ書き込み
    output                      oFull,      // 最大書き込み時High
    output  [pFifoBitWidth-1:0] oRd,        // read data
    input                       iRe,        // read enable
    output                      oRvd,       // 有効データ出力
    output                      oEmp,       // バッファ空時High
    input                       inARST,
    input                       iCLK
);

//----------------------------------------------------------
// FIFO の深さの bit幅取得
//----------------------------------------------------------
localparam pAddrWidth  = fBitWidth(pFifoDepth);


//-----------------------------------------------------------------------------
// アドレスの更新
//-----------------------------------------------------------------------------
reg  [pAddrWidth-1:0] rWa, rRa;
wire [pAddrWidth-1:0] wWa = rWa + 1'b1;
reg  qWe,qRe;
reg  qFull;							assign oFull = qFull;
reg  qEmp;							assign oEmp = qEmp;
reg  rRe;							assign oRvd = rRe;

always @(posedge iCLK, negedge inARST)
begin
	if (!inARST)	rWa <= {pAddrWidth{1'b0}};
	else if	(qWe)	rWa <= wWa;
	else 			rWa <= rWa;

	if (!inARST)	rRa <= {pAddrWidth{1'b0}};
	else if	(qRe)	rRa <= rRa + 1'b1;
	else 			rRa <= rRa;

	if (!inARST)	rRe <= 1'b0;
	else if	(qRe)	rRe <= 1'b1;
	else 			rRe <= 1'b0;
end

always @*
begin
	qFull <= (wWa == rRa);
	qEmp <= (rWa == rRa); 
	qWe <= iWe & (~qFull);
	qRe <= iRe & (~qEmp);
end


//-----------------------------------------------------------------------------
// BRAM
//-----------------------------------------------------------------------------
DualPortBramTrion #(
    .pBuffDepth(pFifoDepth),
    .pBitWidth(pFifoBitWidth),
    .pAddrWidth(pAddrWidth),
	.pFifoBlockRam(pFifoBlockRam)
) DualPortBramTrion (
	.iWd(iWd),
	.iWa(rWa),
	.iWe(qWe),
	.oRd(oRd),
	.iRa(rRa),
	.iCLK(iCLK)
);


//-----------------------------------------------------------------------------
// msb側の1を検出しbit幅を取得する
//-----------------------------------------------------------------------------
function[  7:0]	fBitWidth;
    input [31:0] iVAL;
    integer			i;

    begin
    // fBitWidth = 1;
        for (i = 0; i < 32; i = i+1 )
        begin
            if (iVAL[i]) 
            begin
                fBitWidth = i+1;
            end
        end

        if (fBitWidth != 1)
        begin
            fBitWidth = fBitWidth - 1;
        end
    end
endfunction
endmodule

Efinix/Trion/K5Stack10_MIDI/src/common/fifo/sim/SyncFifoController_tb.v
`timescale 1ns / 1ps
//----------------------------------------------------------
// Create  2022/08/12
// Author  KoutaKimura
// SPI の Master Slave を切り替えながらデータの送受信を行う。
// 
//----------------------------------------------------------
module SyncFifoController_tb;

//----------------------------------------------------------
// Top Module Connect
//----------------------------------------------------------
localparam	lpSysClkCycle   = 2;	// CLK サイクル
localparam	lpSimlationTime = 2000;	// シミュレーション時間を指定
// parameter [3:0]		pBlockConnectNum		= 10; 				// Busに接続する Slave数 最大16
// parameter [3:0]		pBlockConnectNumWidth 	= pBlockConnectNum - 1'b1;	// Busに接続する Slave数 最大16

//----------------------------------------------------------
// System Clk Generator
//----------------------------------------------------------
reg	rSCLK = 0;
reg	rSRST = 1;	//初期値
reg	rnSRST = 0;	//初期値

always
begin
    #(lpSysClkCycle/2);
    rSCLK = ~rSCLK;
end

// Reset 処理
task reset_init;
begin
	#(lpSysClkCycle * 5);
	rnSRST = ~rnSRST;
	rSRST = ~rSRST;
	#(lpSysClkCycle * 5);
end
endtask 

//-----------------------------------------------------------------------------
// Fifo Read Write Tester
//-----------------------------------------------------------------------------
localparam lpFifoDepth		= 16;
localparam lpFifoBitWidth 	= 4;

reg  [lpFifoBitWidth-1:0] rWd, rRd;
wire [lpFifoBitWidth-1:0] wRd;
reg  qWe, qRe;
wire wFull, wEmp;
wire wRvd;

SyncFifoController #(
	.pFifoDepth(lpFifoDepth),
	.pFifoBitWidth(lpFifoBitWidth)
) SyncFifoController (
	.iWd(rWd),
	.iWe(qWe),
	.oFull(wFull),
	.oRd(wRd),
	.iRe(qRe),
	.oRvd(wRvd),
	.oEmp(wEmp),
	// CLK Reset
	.inARST(rnSRST),
	.iCLK(rSCLK)
);

always @(posedge rSCLK)
begin
	if (wRvd) 	rRd <= wRd;
	else 		rRd <= rRd;
end

//-----------------------------------------------------------------------------
// FIFO の書き込み読み込みタイミングの調整と WD 生成
//-----------------------------------------------------------------------------
wire wTimingGen;

PulseGenerator #(
	.pSysClk(1),
	.pTimeCke(1),
	.pStartPulse(0)
) PulseGenerator (
	.oPulse(wTimingGen),
	.iRST(rSRST),
	.iCLK(rSCLK)
);

always @(posedge rSCLK)
begin
	if (rSRST) 		rWd <= 0;
	else if (qWe)	rWd <= rWd + 1'b1;
	else 			rWd <= rWd;
end

always @*
begin
	qWe <= ~wFull;
	qRe <= ~wEmp  & wTimingGen;
end

//----------------------------------------------------------
// Simlation Start
//----------------------------------------------------------
initial
begin
	$dumpfile("SyncFifoController_tb.vcd");
	$dumpvars(0, SyncFifoController_tb);	// 引数0:下位モジュール表示, 1:Topのみ
	reset_init();
	#(lpSimlationTime);
    $finish;
end


endmodule

Efinix/Trion/K5Stack10_MIDI/src/common/fifo/sim/SyncFifoController_tb.vcd
$date
	Fri May  5 14:54:31 2023
$end
$version
	Icarus Verilog
$end
$timescale
	1ps
$end
$scope module SyncFifoController_tb $end
$var wire 1 ! wTimingGen $end
$var wire 1 " wRvd $end
$var wire 4 # wRd [3:0] $end
$var wire 1 $ wFull $end
$var wire 1 % wEmp $end
$var reg 1 & qRe $end
$var reg 1 ' qWe $end
$var reg 4 ( rRd [3:0] $end
$var reg 1 ) rSCLK $end
$var reg 1 * rSRST $end
$var reg 4 + rWd [3:0] $end
$var reg 1 , rnSRST $end
$scope module PulseGenerator $end
$var wire 1 ) iCLK $end
$var wire 1 * iRST $end
$var wire 1 ! oPulse $end
$var reg 1 - qCke $end
$var reg 1 . qTimeCke $end
$var reg 1 / rPulse $end
$var reg 8 0 rTimeCkeCnt [7:0] $end
$var reg 1 1 rTmpCount $end
$scope function fBitWidth $end
$var reg 32 2 iVAL [31:0] $end
$var integer 32 3 i [31:0] $end
$upscope $end
$upscope $end
$scope module SyncFifoController $end
$var wire 1 ) iCLK $end
$var wire 1 & iRe $end
$var wire 4 4 iWd [3:0] $end
$var wire 1 ' iWe $end
$var wire 1 , inARST $end
$var wire 1 % oEmp $end
$var wire 1 $ oFull $end
$var wire 1 " oRvd $end
$var wire 4 5 wWa [3:0] $end
$var wire 4 6 oRd [3:0] $end
$var reg 1 7 qEmp $end
$var reg 1 8 qFull $end
$var reg 1 9 qRe $end
$var reg 1 : qWe $end
$var reg 4 ; rRa [3:0] $end
$var reg 1 < rRe $end
$var reg 4 = rWa [3:0] $end
$scope function fBitWidth $end
$var reg 32 > iVAL [31:0] $end
$var integer 32 ? i [31:0] $end
$upscope $end
$scope module DualPortBramTrion $end
$var wire 1 ) iCLK $end
$var wire 4 @ iRa [3:0] $end
$var wire 4 A iWa [3:0] $end
$var wire 4 B iWd [3:0] $end
$var wire 1 : iWe $end
$var wire 4 C oRd [3:0] $end
$var reg 4 D rRd [3:0] $end
$upscope $end
$upscope $end
$scope task reset_init $end
$upscope $end
$upscope $end
$enddefinitions $end
#0
$dumpvars
bx D
bx C
bx B
b0 A
b0 @
bx ?
bx >
b0 =
0<
b0 ;
1:
09
08
17
bx 6
b1 5
bx 4
bx 3
bx 2
x1
bx 0
x/
x.
x-
0,
bx +
1*
0)
bx (
1'
0&
1%
0$
bx #
0"
x!
$end
#1000
0.
1-
01
b0 0
0!
0/
b0 +
b0 4
b0 B
1)
#2000
0)
#3000
1)
#4000
0)
#5000
b0 #
b0 6
b0 C
b0 D
1)
#6000
0)
#7000
1)
#8000
0)
#9000
1)
#10000
0)
0*
1,
#11000
1.
0%
07
b1 +
b1 4
b1 B
b1 0
b10 5
b1 =
b1 A
1)
#12000
0)
#13000
19
0.
1&
b0 0
1!
1/
b10 +
b10 4
b10 B
b11 5
b10 =
b10 A
1)
#14000
0)
#15000
1.
b11 +
b11 4
b11 B
b1 0
1"
1<
b1 ;
b1 @
b100 5
b11 =
b11 A
1)
#16000
0)
#17000
09
0.
0&
b1 #
b1 6
b1 C
b1 D
b0 0
0!
0/
b0 (
b100 +
b100 4
b100 B
b10 ;
b10 @
b101 5
b100 =
b100 A
1)
#18000
0)
#19000
1.
b101 +
b101 4
b101 B
b1 (
b1 0
b10 #
b10 6
b10 C
b10 D
0"
0<
b110 5
b101 =
b101 A
1)
#20000
0)
#21000
19
0.
1&
b0 0
1!
1/
b110 +
b110 4
b110 B
b111 5
b110 =
b110 A
1)
#22000
0)
#23000
1.
b111 +
b111 4
b111 B
b1 0
1"
1<
b11 ;
b11 @
b1000 5
b111 =
b111 A
1)
#24000
0)
#25000
09
0.
0&
b11 #
b11 6
b11 C
b11 D
b0 0
0!
0/
b10 (
b1000 +
b1000 4
b1000 B
b100 ;
b100 @
b1001 5
b1000 =
b1000 A
1)
#26000
0)
#27000
1.
b1001 +
b1001 4
b1001 B
b11 (
b1 0
b100 #
b100 6
b100 C
b100 D
0"
0<
b1010 5
b1001 =
b1001 A
1)
#28000
0)
#29000
19
0.
1&
b0 0
1!
1/
b1010 +
b1010 4
b1010 B
b1011 5
b1010 =
b1010 A
1)
#30000
0)
#31000
1.
b1011 +
b1011 4
b1011 B
b1 0
1"
1<
b101 ;
b101 @
b1100 5
b1011 =
b1011 A
1)
#32000
0)
#33000
09
0.
0&
b101 #
b101 6
b101 C
b101 D
b0 0
0!
0/
b100 (
b1100 +
b1100 4
b1100 B
b110 ;
b110 @
b1101 5
b1100 =
b1100 A
1)
#34000
0)
#35000
1.
b1101 +
b1101 4
b1101 B
b101 (
b1 0
b110 #
b110 6
b110 C
b110 D
0"
0<
b1110 5
b1101 =
b1101 A
1)
#36000
0)
#37000
19
0.
1&
b0 0
1!
1/
b1110 +
b1110 4
b1110 B
b1111 5
b1110 =
b1110 A
1)
#38000
0)
#39000
1.
b1111 +
b1111 4
b1111 B
b1 0
1"
1<
b111 ;
b111 @
b0 5
b1111 =
b1111 A
1)
#40000
0)
#41000
09
0.
0&
b111 #
b111 6
b111 C
b111 D
b0 0
0!
0/
b110 (
b0 +
b0 4
b0 B
b1000 ;
b1000 @
b1 5
b0 =
b0 A
1)
#42000
0)
#43000
1.
b1 +
b1 4
b1 B
b111 (
b1 0
b1000 #
b1000 6
b1000 C
b1000 D
0"
0<
b10 5
b1 =
b1 A
1)
#44000
0)
#45000
19
0.
1&
b0 0
1!
1/
b10 +
b10 4
b10 B
b11 5
b10 =
b10 A
1)
#46000
0)
#47000
1.
b11 +
b11 4
b11 B
b1 0
1"
1<
b1001 ;
b1001 @
b100 5
b11 =
b11 A
1)
#48000
0)
#49000
09
0.
0&
b1001 #
b1001 6
b1001 C
b1001 D
b0 0
0!
0/
b1000 (
b100 +
b100 4
b100 B
b1010 ;
b1010 @
b101 5
b100 =
b100 A
1)
#50000
0)
#51000
1.
b101 +
b101 4
b101 B
b1001 (
b1 0
b1010 #
b1010 6
b1010 C
b1010 D
0"
0<
b110 5
b101 =
b101 A
1)
#52000
0)
#53000
19
0.
1&
b0 0
1!
1/
b110 +
b110 4
b110 B
b111 5
b110 =
b110 A
1)
#54000
0)
#55000
1.
b111 +
b111 4
b111 B
b1 0
1"
1<
b1011 ;
b1011 @
b1000 5
b111 =
b111 A
1)
#56000
0)
#57000
09
0.
0&
b1011 #
b1011 6
b1011 C
b1011 D
b0 0
0!
0/
b1010 (
b1000 +
b1000 4
b1000 B
b1100 ;
b1100 @
b1001 5
b1000 =
b1000 A
1)
#58000
0)
#59000
1.
b1001 +
b1001 4
b1001 B
b1011 (
b1 0
b1100 #
b1100 6
b1100 C
b1100 D
0"
0<
b1010 5
b1001 =
b1001 A
1)
#60000
0)
#61000
19
0.
1&
b0 0
1!
1/
b1010 +
b1010 4
b1010 B
b1011 5
b1010 =
b1010 A
1)
#62000
0)
#63000
1.
b1011 +
b1011 4
b1011 B
b1 0
1"
1<
b1101 ;
b1101 @
b1100 5
b1011 =
b1011 A
1)
#64000
0)
#65000
09
0.
0&
b1101 #
b1101 6
b1101 C
b1101 D
b0 0
0!
0/
b1100 (
b1100 +
b1100 4
b1100 B
b1110 ;
b1110 @
b1101 5
b1100 =
b1100 A
1)
#66000
0)
#67000
0:
0'
1.
1$
18
b1101 +
b1101 4
b1101 B
b1101 (
b1 0
b1110 #
b1110 6
b1110 C
b1110 D
0"
0<
b1110 5
b1101 =
b1101 A
1)
#68000
0)
#69000
19
0.
1&
b0 0
1!
1/
1)
#70000
0)
#71000
1:
1'
1.
0$
08
b1 0
1"
1<
b1111 ;
b1111 @
1)
#72000
0)
#73000
09
0.
0&
b1111 #
b1111 6
b1111 C
b1111 D
b0 0
0!
0/
b1110 (
b1110 +
b1110 4
b1110 B
b0 ;
b0 @
b1111 5
b1110 =
b1110 A
1)
#74000
0)
#75000
0:
0'
1.
1$
18
b1111 +
b1111 4
b1111 B
b1111 (
b1 0
b0 #
b0 6
b0 C
b0 D
0"
0<
b0 5
b1111 =
b1111 A
1)
#76000
0)
#77000
19
0.
1&
b0 0
1!
1/
1)
#78000
0)
#79000
1:
1'
1.
0$
08
b1 0
1"
1<
b1 ;
b1 @
1)
#80000
0)
#81000
09
0.
0&
b1 #
b1 6
b1 C
b1 D
b0 0
0!
0/
b0 (
b0 +
b0 4
b0 B
b10 ;
b10 @
b1 5
b0 =
b0 A
1)
#82000
0)
#83000
0:
0'
1.
1$
18
b1 +
b1 4
b1 B
b1 (
b1 0
b10 #
b10 6
b10 C
b10 D
0"
0<
b10 5
b1 =
b1 A
1)
#84000
0)
#85000
19
0.
1&
b0 0
1!
1/
1)
#86000
0)
#87000
1:
1'
1.
0$
08
b1 0
1"
1<
b11 ;
b11 @
1)
#88000
0)
#89000
09
0.
0&
b11 #
b11 6
b11 C
b11 D
b0 0
0!
0/
b10 (
b10 +
b10 4
b10 B
b100 ;
b100 @
b11 5
b10 =
b10 A
1)
#90000
0)
#91000
0:
0'
1.
1$
18
b11 +
b11 4
b11 B
b11 (
b1 0
b100 #
b100 6
b100 C
b100 D
0"
0<
b100 5
b11 =
b11 A
1)
#92000
0)
#93000
19
0.
1&
b0 0
1!
1/
1)
#94000
0)
#95000
1:
1'
1.
0$
08
b1 0
1"
1<
b101 ;
b101 @
1)
#96000
0)
#97000
09
0.
0&
b101 #
b101 6
b101 C
b101 D
b0 0
0!
0/
b100 (
b100 +
b100 4
b100 B
b110 ;
b110 @
b101 5
b100 =
b100 A
1)
#98000
0)
#99000
0:
0'
1.
1$
18
b101 +
b101 4
b101 B
b101 (
b1 0
b110 #
b110 6
b110 C
b110 D
0"
0<
b110 5
b101 =
b101 A
1)
#100000
0)
#101000
19
0.
1&
b0 0
1!
1/
1)
#102000
0)
#103000
1:
1'
1.
0$
08
b1 0
1"
1<
b111 ;
b111 @
1)
#104000
0)
#105000
09
0.
0&
b111 #
b111 6
b111 C
b111 D
b0 0
0!
0/
b110 (
b110 +
b110 4
b110 B
b1000 ;
b1000 @
b111 5
b110 =
b110 A
1)
#106000
0)
#107000
0:
0'
1.
1$
18
b111 +
b111 4
b111 B
b111 (
b1 0
b1000 #
b1000 6
b1000 C
b1000 D
0"
0<
b1000 5
b111 =
b111 A
1)
#108000
0)
#109000
19
0.
1&
b0 0
1!
1/
1)
#110000
0)
#111000
1:
1'
1.
0$
08
b1 0
1"
1<
b1001 ;
b1001 @
1)
#112000
0)
#113000
09
0.
0&
b1001 #
b1001 6
b1001 C
b1001 D
b0 0
0!
0/
b1000 (
b1000 +
b1000 4
b1000 B
b1010 ;
b1010 @
b1001 5
b1000 =
b1000 A
1)
#114000
0)
#115000
0:
0'
1.
1$
18
b1001 +
b1001 4
b1001 B
b1001 (
b1 0
b1010 #
b1010 6
b1010 C
b1010 D
0"
0<
b1010 5
b1001 =
b1001 A
1)
#116000
0)
#117000
19
0.
1&
b0 0
1!
1/
1)
#118000
0)
#119000
1:
1'
1.
0$
08
b1 0
1"
1<
b1011 ;
b1011 @
1)
#120000
0)
#121000
09
0.
0&
b1011 #
b1011 6
b1011 C
b1011 D
b0 0
0!
0/
b1010 (
b1010 +
b1010 4
b1010 B
b1100 ;
b1100 @
b1011 5
b1010 =
b1010 A
1)
#122000
0)
#123000
0:
0'
1.
1$
18
b1011 +
b1011 4
b1011 B
b1011 (
b1 0
b1100 #
b1100 6
b1100 C
b1100 D
0"
0<
b1100 5
b1011 =
b1011 A
1)
#124000
0)
#125000
19
0.
1&
b0 0
1!
1/
1)
#126000
0)
#127000
1:
1'
1.
0$
08
b1 0
1"
1<
b1101 ;
b1101 @
1)
#128000
0)
#129000
09
0.
0&
b1101 #
b1101 6
b1101 C
b1101 D
b0 0
0!
0/
b1100 (
b1100 +
b1100 4
b1100 B
b1110 ;
b1110 @
b1101 5
b1100 =
b1100 A
1)
#130000
0)
#131000
0:
0'
1.
1$
18
b1101 +
b1101 4
b1101 B
b1101 (
b1 0
b1110 #
b1110 6
b1110 C
b1110 D
0"
0<
b1110 5
b1101 =
b1101 A
1)
#132000
0)
#133000
19
0.
1&
b0 0
1!
1/
1)
#134000
0)
#135000
1:
1'
1.
0$
08
b1 0
1"
1<
b1111 ;
b1111 @
1)
#136000
0)
#137000
09
0.
0&
b1111 #
b1111 6
b1111 C
b1111 D
b0 0
0!
0/
b1110 (
b1110 +
b1110 4
b1110 B
b0 ;
b0 @
b1111 5
b1110 =
b1110 A
1)
#138000
0)
#139000
0:
0'
1.
1$
18
b1111 +
b1111 4
b1111 B
b1111 (
b1 0
b0 #
b0 6
b0 C
b0 D
0"
0<
b0 5
b1111 =
b1111 A
1)
#140000
0)
#141000
19
0.
1&
b0 0
1!
1/
1)
#142000
0)
#143000
1:
1'
1.
0$
08
b1 0
1"
1<
b1 ;
b1 @
1)
#144000
0)
#145000
09
0.
0&
b1 #
b1 6
b1 C
b1 D
b0 0
0!
0/
b0 (
b0 +
b0 4
b0 B
b10 ;
b10 @
b1 5
b0 =
b0 A
1)
#146000
0)
#147000
0:
0'
1.
1$
18
b1 +
b1 4
b1 B
b1 (
b1 0
b10 #
b10 6
b10 C
b10 D
0"
0<
b10 5
b1 =
b1 A
1)
#148000
0)
#149000
19
0.
1&
b0 0
1!
1/
1)
#150000
0)
#151000
1:
1'
1.
0$
08
b1 0
1"
1<
b11 ;
b11 @
1)
#152000
0)
#153000
09
0.
0&
b11 #
b11 6
b11 C
b11 D
b0 0
0!
0/
b10 (
b10 +
b10 4
b10 B
b100 ;
b100 @
b11 5
b10 =
b10 A
1)
#154000
0)
#155000
0:
0'
1.
1$
18
b11 +
b11 4
b11 B
b11 (
b1 0
b100 #
b100 6
b100 C
b100 D
0"
0<
b100 5
b11 =
b11 A
1)
#156000
0)
#157000
19
0.
1&
b0 0
1!
1/
1)
#158000
0)
#159000
1:
1'
1.
0$
08
b1 0
1"
1<
b101 ;
b101 @
1)
#160000
0)
#161000
09
0.
0&
b101 #
b101 6
b101 C
b101 D
b0 0
0!
0/
b100 (
b100 +
b100 4
b100 B
b110 ;
b110 @
b101 5
b100 =
b100 A
1)
#162000
0)
#163000
0:
0'
1.
1$
18
b101 +
b101 4
b101 B
b101 (
b1 0
b110 #
b110 6
b110 C
b110 D
0"
0<
b110 5
b101 =
b101 A
1)
#164000
0)
#165000
19
0.
1&
b0 0
1!
1/
1)
#166000
0)
#167000
1:
1'
1.
0$
08
b1 0
1"
1<
b111 ;
b111 @
1)
#168000
0)
#169000
09
0.
0&
b111 #
b111 6
b111 C
b111 D
b0 0
0!
0/
b110 (
b110 +
b110 4
b110 B
b1000 ;
b1000 @
b111 5
b110 =
b110 A
1)
#170000
0)
#171000
0:
0'
1.
1$
18
b111 +
b111 4
b111 B
b111 (
b1 0
b1000 #
b1000 6
b1000 C
b1000 D
0"
0<
b1000 5
b111 =
b111 A
1)
#172000
0)
#173000
19
0.
1&
b0 0
1!
1/
1)
#174000
0)
#175000
1:
1'
1.
0$
08
b1 0
1"
1<
b1001 ;
b1001 @
1)
#176000
0)
#177000
09
0.
0&
b1001 #
b1001 6
b1001 C
b1001 D
b0 0
0!
0/
b1000 (
b1000 +
b1000 4
b1000 B
b1010 ;
b1010 @
b1001 5
b1000 =
b1000 A
1)
#178000
0)
#179000
0:
0'
1.
1$
18
b1001 +
b1001 4
b1001 B
b1001 (
b1 0
b1010 #
b1010 6
b1010 C
b1010 D
0"
0<
b1010 5
b1001 =
b1001 A
1)
#180000
0)
#181000
19
0.
1&
b0 0
1!
1/
1)
#182000
0)
#183000
1:
1'
1.
0$
08
b1 0
1"
1<
b1011 ;
b1011 @
1)
#184000
0)
#185000
09
0.
0&
b1011 #
b1011 6
b1011 C
b1011 D
b0 0
0!
0/
b1010 (
b1010 +
b1010 4
b1010 B
b1100 ;
b1100 @
b1011 5
b1010 =
b1010 A
1)
#186000
0)
#187000
0:
0'
1.
1$
18
b1011 +
b1011 4
b1011 B
b1011 (
b1 0
b1100 #
b1100 6
b1100 C
b1100 D
0"
0<
b1100 5
b1011 =
b1011 A
1)
#188000
0)
#189000
19
0.
1&
b0 0
1!
1/
1)
#190000
0)
#191000
1:
1'
1.
0$
08
b1 0
1"
1<
b1101 ;
b1101 @
1)
#192000
0)
#193000
09
0.
0&
b1101 #
b1101 6
b1101 C
b1101 D
b0 0
0!
0/
b1100 (
b1100 +
b1100 4
b1100 B
b1110 ;
b1110 @
b1101 5
b1100 =
b1100 A
1)
#194000
0)
#195000
0:
0'
1.
1$
18
b1101 +
b1101 4
b1101 B
b1101 (
b1 0
b1110 #
b1110 6
b1110 C
b1110 D
0"
0<
b1110 5
b1101 =
b1101 A
1)
#196000
0)
#197000
19
0.
1&
b0 0
1!
1/
1)
#198000
0)
#199000
1:
1'
1.
0$
08
b1 0
1"
1<
b1111 ;
b1111 @
1)
#200000
0)
#201000
09
0.
0&
b1111 #
b1111 6
b1111 C
b1111 D
b0 0
0!
0/
b1110 (
b1110 +
b1110 4
b1110 B
b0 ;
b0 @
b1111 5
b1110 =
b1110 A
1)
#202000
0)
#203000
0:
0'
1.
1$
18
b1111 +
b1111 4
b1111 B
b1111 (
b1 0
b0 #
b0 6
b0 C
b0 D
0"
0<
b0 5
b1111 =
b1111 A
1)
#204000
0)
#205000
19
0.
1&
b0 0
1!
1/
1)
#206000
0)
#207000
1:
1'
1.
0$
08
b1 0
1"
1<
b1 ;
b1 @
1)
#208000
0)
#209000
09
0.
0&
b1 #
b1 6
b1 C
b1 D
b0 0
0!
0/
b0 (
b0 +
b0 4
b0 B
b10 ;
b10 @
b1 5
b0 =
b0 A
1)
#210000
0)
#211000
0:
0'
1.
1$
18
b1 +
b1 4
b1 B
b1 (
b1 0
b10 #
b10 6
b10 C
b10 D
0"
0<
b10 5
b1 =
b1 A
1)
#212000
0)
#213000
19
0.
1&
b0 0
1!
1/
1)
#214000
0)
#215000
1:
1'
1.
0$
08
b1 0
1"
1<
b11 ;
b11 @
1)
#216000
0)
#217000
09
0.
0&
b11 #
b11 6
b11 C
b11 D
b0 0
0!
0/
b10 (
b10 +
b10 4
b10 B
b100 ;
b100 @
b11 5
b10 =
b10 A
1)
#218000
0)
#219000
0:
0'
1.
1$
18
b11 +
b11 4
b11 B
b11 (
b1 0
b100 #
b100 6
b100 C
b100 D
0"
0<
b100 5
b11 =
b11 A
1)
#220000
0)
#221000
19
0.
1&
b0 0
1!
1/
1)
#222000
0)
#223000
1:
1'
1.
0$
08
b1 0
1"
1<
b101 ;
b101 @
1)
#224000
0)
#225000
09
0.
0&
b101 #
b101 6
b101 C
b101 D
b0 0
0!
0/
b100 (
b100 +
b100 4
b100 B
b110 ;
b110 @
b101 5
b100 =
b100 A
1)
#226000
0)
#227000
0:
0'
1.
1$
18
b101 +
b101 4
b101 B
b101 (
b1 0
b110 #
b110 6
b110 C
b110 D
0"
0<
b110 5
b101 =
b101 A
1)
#228000
0)
#229000
19
0.
1&
b0 0
1!
1/
1)
#230000
0)
#231000
1:
1'
1.
0$
08
b1 0
1"
1<
b111 ;
b111 @
1)
#232000
0)
#233000
09
0.
0&
b111 #
b111 6
b111 C
b111 D
b0 0
0!
0/
b110 (
b110 +
b110 4
b110 B
b1000 ;
b1000 @
b111 5
b110 =
b110 A
1)
#234000
0)
#235000
0:
0'
1.
1$
18
b111 +
b111 4
b111 B
b111 (
b1 0
b1000 #
b1000 6
b1000 C
b1000 D
0"
0<
b1000 5
b111 =
b111 A
1)
#236000
0)
#237000
19
0.
1&
b0 0
1!
1/
1)
#238000
0)
#239000
1:
1'
1.
0$
08
b1 0
1"
1<
b1001 ;
b1001 @
1)
#240000
0)
#241000
09
0.
0&
b1001 #
b1001 6
b1001 C
b1001 D
b0 0
0!
0/
b1000 (
b1000 +
b1000 4
b1000 B
b1010 ;
b1010 @
b1001 5
b1000 =
b1000 A
1)
#242000
0)
#243000
0:
0'
1.
1$
18
b1001 +
b1001 4
b1001 B
b1001 (
b1 0
b1010 #
b1010 6
b1010 C
b1010 D
0"
0<
b1010 5
b1001 =
b1001 A
1)
#244000
0)
#245000
19
0.
1&
b0 0
1!
1/
1)
#246000
0)
#247000
1:
1'
1.
0$
08
b1 0
1"
1<
b1011 ;
b1011 @
1)
#248000
0)
#249000
09
0.
0&
b1011 #
b1011 6
b1011 C
b1011 D
b0 0
0!
0/
b1010 (
b1010 +
b1010 4
b1010 B
b1100 ;
b1100 @
b1011 5
b1010 =
b1010 A
1)
#250000
0)
