Xilinx/workspace/ArtyS7/SignalTraining/src/nv_top.v
/*~`^*~`^*~`^*~`^*~`^*~`^*~`^*~`^*~`^*~`^*~`^*~`^*~`^*~`^*~`^*~`^*~`^*~`^*~`^*
 *
 * File Name   : MSignalSystem_NV_Training_03.v
 * Description : 
 * Simulator   : VeritakWin Ver.3.43E Build Mar.20.2008
 * Implem. Tool: ISE... Ver.14.1 Appl Ver. P.15xf
 * Explanation : 新人向けSVM-03ボードを使用したFPGA設計、実装、
 *               Verilog-HDLトレーニング
 *
 *~`^*~`^*~`^*~`^*~`^*~`^*~`^*~`^*~`^*~`^*~`^*~`^*~`^*~`^*~`^*~`^*~`^*~`^*~`^*/
//-----------------------------------------------------------------------------
module nv_top
#(
parameter		pCLKFreqDiv10	= 2500000	// iCLK周波数[Hz]/10を指定
)(
// Car Side Lamp is Blue, Yellow and Red
// Walker Side Lamp is Blue, Red and Display for Wait
output			oCB,	oCY,	oCR,	// Lamp-Out for Car Side Signal
output			oWB,	oWR,	oWD,	// Lamp-Out for Walker Side Signal
//
// Push Button Switch Input
input 			iWPBS,	// Push Button Switch for Walker Side
//
// Common System Lines
input 			iRST,	// System Reset(Sync. Pos.)
input 			iCLK	// System Clock
//
);
  
//-----------------------------------------------------------------------------
// Lamp-Out Port, State Code and Time Const. Definition
//-----------------------------------------------------------------------------
  reg			rCb,	rCy,	rCr;			assign {oCB,oCY,oCR}	= {rCb,rCy,rCr};
  reg			rWb,	rWr,	rWd;			assign {oWB,oWR,oWD}	= {rWb,rWr,rWd};

  localparam[2:0]	// Each State
    lpsCbWrKeep	 = 3'h0,		// oCB=ON, oWR=ON, Other=OFF
    lpsCbWrPass	 = 3'h1,		// lpsCbWr状態に加えlpsCyWrへ遷移するまでの待機
    lpsCyWr			 = 3'h2,
    lpsCrWrInter = 3'h3,
    lpsCrWb			 = 3'h4,
    lpsCrWbBlink = 3'h5,
    lpsCrWrTurn	 = 3'h6;
  // 各Lampの点灯状態の組み合わせで、各ステートを定義
  // WDの点灯状態は信号機としてのランプではないので、あえて含めない。
  
  localparam[3:0]	// Each Count Time[sec]
    lpctCbWrKeep  = 4'd10,
    lpctCbWrPass  = 4'd1,
    lpctCyWr		  = 4'd2,
    lpctCrWr		  = 4'd1,
    lpctCrWb		  = 4'd7,
    lpctCrWbBlink	= 4'd4;
  // 各Lampの点灯状態での点灯または点滅時間を定義
  // 各ステートの滞在を示す時間となる。
    
//-----------------------------------------------------------------------------
  // ※. ここに合成可能なRTLにて実装してください。
/* 
 * 出力信号 | 機能 | 対応レジスタ
 * oWB 歩行者青信号 reg rWb
 * oWR 歩行者赤信号 reg rWr
 * oWD 何かのランプ reg rWd
 *
 * oCB 車道青信号     reg rCb
 * oCY 車道黄色信号   reg rCy
 * oCR 車道赤信号     reg rCr
 *
 * 基本的な信号動作順序
 * 
 * 0. ユーザーがスイッチを押す
 * 1. 車道側の信号が青、黄、赤の順に切り替わる
 * 2. 歩道側の信号が赤、青に切り替わる
 * 3. 歩道側の信号青が点滅する
 * 4. 歩道側の信号が赤に切り替わる
 * 5. 車道側の信号が青に切り替わる
 */

reg [24:0] tmp_count;  // 最大クロック数のカウント値を保存
reg [6:0]  sec_count;  // 各状態の経過時間を保存
reg [6:0]  state_time; // 各状態で指定された点灯時間を保存
reg [2:0]  lamp_state; // LEDの状態遷移を管理
reg state_start;       // ボタン押下時の状態開始フラグを管理

wire ENABLE;           // 10hz周期のenable信号
wire STATE_START;      // 状態開始フラグ信号

assign ENABLE = ((tmp_count[21:0] == (pCLKFreqDiv10 - 1)) && (STATE_START == 1'd1)) ? 1'd1 : 1'd0; // 10HzでENABLEが立ち上げ
assign STATE_START = state_start;


// ENABLEカウンター
always @(posedge iCLK) begin
  if (iRST == 1'd1) begin
    tmp_count <= 25'd0;
  end else if ((ENABLE == 1'd1) || (STATE_START == 1'd0)) begin
    tmp_count <= 25'd0;
  end else begin
    tmp_count <= tmp_count + 25'd1;
  end
end

// Btn押下時の状態遷移開始、状態終了まで1をキープする
always @(posedge iCLK) begin
  if (iRST == 1'd1) begin
    state_start <= 1'd0;
  end else if (iWPBS == 1'b1) begin
    state_start <= 1'd1;
  end else if ((ENABLE == 1'b1) && (lamp_state == lpsCrWrTurn) && (sec_count == state_time)) begin // 最終状態切替時にstartflag off
    state_start <= 1'd0;
  end
end

// 指定時間カウント用カウンター
always @(posedge iCLK) begin
  if (iRST == 1'b1) begin
    sec_count <= 7'd0;
  end else if ((ENABLE == 1'd1) && (STATE_START == 1'd1)) begin
    if (sec_count == state_time) begin
      sec_count <= 7'd0;
    end else begin
      sec_count <= sec_count + 7'd1;
    end
  end
end

// ランプ状態遷移、指定時間経過したら処理
always @(posedge iCLK) begin
  if (iRST == 1'b1) begin
    lamp_state <= lpsCbWrKeep;
  end else if ((ENABLE == 1'd1) && (STATE_START == 1'd1) && (sec_count == state_time)) begin
    if (lamp_state == lpsCrWrTurn) begin
      lamp_state <= lpsCbWrKeep;
    end else begin
      lamp_state <= lamp_state + 3'd1;
    end
  end
end

// ランプ点灯パターン・時間切替
always @(lamp_state or ENABLE) begin
  case (lamp_state)
    lpsCbWrKeep: begin // 車道青点灯、歩道赤点灯、他消灯
      rCb <= 1'd1;
      rCy <= 1'd0;
      rCr <= 1'd0;
      rWb <= 1'd0;
      rWr <= 1'd1;
      rWd <= 1'd0;
      state_time <= lpctCbWrKeep;
    end

    lpsCbWrPass: begin // lpsCyWr遷移までKeepと同じ動作を行う
      rCb <= 1'd1;
      rCy <= 1'd0;
      rCr <= 1'd0;
      rWb <= 1'd0;
      rWr <= 1'd1;
      rWd <= 1'd0;
      state_time <= lpctCbWrPass;
    end

    lpsCyWr: begin // 車道黄点灯、歩道赤点灯、他消灯
      rCb <= 1'd0;
      rCy <= 1'd1;
      rCr <= 1'd0;
      rWb <= 1'd0;
      rWr <= 1'd1;
      rWd <= 1'd0;
      state_time <= lpctCyWr;
    end

    lpsCrWrInter: begin // 車道赤点灯、歩道赤点灯、他消灯
      rCb <= 1'd0;
      rCy <= 1'd0;
      rCr <= 1'd1;
      rWb <= 1'd0;
      rWr <= 1'd1;
      rWd <= 1'd0;
      state_time <= lpctCrWr;
    end

    lpsCrWb: begin // 車道赤点灯、歩道青信号点灯、他消灯
      rCb <= 1'd0;
      rCy <= 1'd0;
      rCr <= 1'd1;
      rWb <= 1'd1;
      rWr <= 1'd0;
      rWd <= 1'd0;
      state_time <= lpctCrWb;
    end

    lpsCrWbBlink: begin // 車道赤点灯、歩道青信号点滅、他消灯
      rCb <= 1'd0;
      rCy <= 1'd0;
      rCr <= 1'd1;
      rWb <= (ENABLE == 1'b1) ? rWb ^ 1'b1 : rWb;
      rWr <= 1'd0;
      rWd <= 1'd0;
      state_time <= lpctCrWbBlink;
    end

    lpsCrWrTurn: begin // 車道赤点灯、歩道赤点灯、他消灯
      rCb <= 1'd0;
      rCy <= 1'd0;
      rCr <= 1'd1;
      rWb <= 1'd0;
      rWr <= 1'd1;
      rWd <= 1'd0;
      state_time <= 7'd1;
    end

    default: begin // 操作が無ければ車道青点灯、歩道赤点灯
      rCb <= 1'd1;
      rCy <= 1'd0;
      rCr <= 1'd0;
      rWb <= 1'd0;
      rWr <= 1'd1;
      rWd <= 1'd1;
      state_time <= 7'd0;
    end
  endcase
end


//-----------------------------------------------------------------------------
endmodule  // MTopSvm03_NV_Training_03
//-----------------------------------------------------------------------------

Xilinx/workspace/ArtyS7/SignalTraining/src/nv_tb.v
`timescale 1ns / 1ps
//////////////////////////////////////////////////////////////////////////////////
// Company: 
// Engineer: 
// 
// Create Date: 2021/10/21 21:14:39
// Design Name: 
// Module Name: nv_tb
// Project Name: 
// Target Devices: 
// Tool Versions: 
// Description: 
// 
// Dependencies: 
// 
// Revision:
// Revision 0.01 - File Created
// Additional Comments:
// 
//////////////////////////////////////////////////////////////////////////////////
module nv_tb;

wire CarBlue, CarYellow, CarRed;
wire WarkBlue, WarkRed, WarkDled;
reg  sw, reset, clk;

parameter CYCLE = 20;
parameter SIM_MAX = 4;
parameter LOOP = 1;

integer i;

nv_top #(.pCLKFreqDiv10(SIM_MAX))
        i0(.oCB(CarBlue), .oCY(CarYellow), .oCR(CarRed),
            .oWB(WarkBlue), .oWR(WarkRed), .oWD(WarkDled),
            .iWPBS(sw), .iRST(reset), .iCLK(clk));

always begin
    #(CYCLE/2)
    clk = ~clk;
end

initial begin
    clk = 1'b0;
    reset = 1'b1;
    #CYCLE reset = 1'd0;

    for (i = 0; i < LOOP; i = i + 1) begin
        #CYCLE sw = 1'd1;
        #CYCLE sw = 1'd0;
        #(CYCLE * SIM_MAX * 20);
    end
    #(CYCLE * SIM_MAX * 20);
    $finish;
end

initial begin
	// $monitor("CLK=%d, RES=%d, Q=%d", CLK, RES, Q);
	$dumpfile("led.vcd");
	$dumpvars(0, nv_tb);
end


endmodule

Xilinx/workspace/ArtyS7/Led/src/led.vcd
$date
	Sat Nov 20 20:00:21 2021
$end
$version
	Icarus Verilog
$end
$timescale
	1ps
$end
$scope module nv_tb $end
$var wire 1 ! WarkRed $end
$var wire 1 " WarkDled $end
$var wire 1 # WarkBlue $end
$var wire 1 $ CarYellow $end
$var wire 1 % CarRed $end
$var wire 1 & CarBlue $end
$var reg 1 ' clk $end
$var reg 1 ( reset $end
$var reg 1 ) sw $end
$var integer 32 * i [31:0] $end
$scope module i0 $end
$var wire 1 ' iCLK $end
$var wire 1 ( iRST $end
$var wire 1 ) iWPBS $end
$var wire 1 ! oWR $end
$var wire 1 " oWD $end
$var wire 1 # oWB $end
$var wire 1 $ oCY $end
$var wire 1 % oCR $end
$var wire 1 & oCB $end
$var wire 1 + STATE_START $end
$var wire 1 , ENABLE $end
$var reg 3 - lamp_state [2:0] $end
$var reg 1 . rCb $end
$var reg 1 / rCr $end
$var reg 1 0 rCy $end
$var reg 1 1 rWb $end
$var reg 1 2 rWd $end
$var reg 1 3 rWr $end
$var reg 7 4 sec_count [6:0] $end
$var reg 1 + state_start $end
$var reg 7 5 state_time [6:0] $end
$var reg 25 6 tmp_count [24:0] $end
$upscope $end
$upscope $end
$enddefinitions $end
#0
$dumpvars
bx 6
b0 5
bx 4
13
12
01
00
0/
1.
bx -
x,
x+
bx *
x)
1(
0'
1&
0%
0$
0#
1"
1!
$end
#10000
0"
b1010 5
02
0,
b0 6
0+
b0 4
b0 -
1'
#20000
0'
b0 *
0(
#30000
1'
#40000
0'
1)
#50000
1+
1'
#60000
0'
0)
#70000
b1 6
1'
#80000
0'
#90000
b10 6
1'
#100000
0'
#110000
1,
b11 6
1'
#120000
0'
#130000
0,
b0 6
b1 4
1'
#140000
0'
#150000
b1 6
1'
#160000
0'
#170000
b10 6
1'
#180000
0'
#190000
1,
b11 6
1'
#200000
0'
#210000
0,
b0 6
b10 4
1'
#220000
0'
#230000
b1 6
1'
#240000
0'
#250000
b10 6
1'
#260000
0'
#270000
1,
b11 6
1'
#280000
0'
#290000
0,
b0 6
b11 4
1'
#300000
0'
#310000
b1 6
1'
#320000
0'
#330000
b10 6
1'
#340000
0'
#350000
1,
b11 6
1'
#360000
0'
#370000
0,
b0 6
b100 4
1'
#380000
0'
#390000
b1 6
1'
#400000
0'
#410000
b10 6
1'
#420000
0'
#430000
1,
b11 6
1'
#440000
0'
#450000
0,
b0 6
b101 4
1'
#460000
0'
#470000
b1 6
1'
#480000
0'
#490000
b10 6
1'
#500000
0'
#510000
1,
b11 6
1'
#520000
0'
#530000
0,
b0 6
b110 4
1'
#540000
0'
#550000
b1 6
1'
#560000
0'
#570000
b10 6
1'
#580000
0'
#590000
1,
b11 6
1'
#600000
0'
#610000
0,
b0 6
b111 4
1'
#620000
0'
#630000
b1 6
1'
#640000
0'
#650000
b10 6
1'
#660000
0'
#670000
1,
b11 6
1'
#680000
0'
#690000
0,
b0 6
b1000 4
1'
#700000
0'
#710000
b1 6
1'
#720000
0'
#730000
b10 6
1'
#740000
0'
#750000
1,
b11 6
1'
#760000
0'
#770000
0,
b0 6
b1001 4
1'
#780000
0'
#790000
b1 6
1'
#800000
0'
#810000
b10 6
1'
#820000
0'
#830000
1,
b11 6
1'
#840000
0'
#850000
0,
b0 6
b1010 4
1'
#860000
0'
#870000
b1 6
1'
#880000
0'
#890000
b10 6
1'
#900000
0'
#910000
1,
b11 6
1'
#920000
0'
#930000
b1 5
0,
b0 6
b0 4
b1 -
1'
#940000
0'
#950000
b1 6
1'
#960000
0'
#970000
b10 6
1'
#980000
0'
#990000
1,
b11 6
1'
#1000000
0'
#1010000
0,
b0 6
b1 4
1'
#1020000
0'
#1030000
b1 6
1'
#1040000
0'
#1050000
b10 6
1'
#1060000
0'
#1070000
1,
b11 6
1'
#1080000
0'
#1090000
1$
0&
b10 5
10
0.
0,
b0 6
b0 4
b10 -
1'
#1100000
0'
#1110000
b1 6
1'
#1120000
0'
#1130000
b10 6
1'
#1140000
0'
#1150000
1,
b11 6
1'
#1160000
0'
#1170000
0,
b0 6
b1 4
1'
#1180000
0'
#1190000
b1 6
1'
#1200000
0'
#1210000
b10 6
1'
#1220000
0'
#1230000
1,
b11 6
1'
#1240000
0'
#1250000
0,
b0 6
b10 4
1'
#1260000
0'
#1270000
b1 6
1'
#1280000
0'
#1290000
b10 6
1'
#1300000
0'
#1310000
1,
b11 6
1'
#1320000
0'
#1330000
1%
0$
b1 5
1/
00
0,
b0 6
b0 4
b11 -
1'
#1340000
0'
#1350000
b1 6
1'
#1360000
0'
#1370000
b10 6
1'
#1380000
0'
#1390000
1,
b11 6
1'
#1400000
0'
#1410000
0,
b0 6
b1 4
1'
#1420000
0'
#1430000
b1 6
1'
#1440000
0'
#1450000
b10 6
1'
#1460000
0'
#1470000
1,
b11 6
1'
#1480000
0'
#1490000
0!
1#
b111 5
03
11
0,
b0 6
b0 4
b100 -
1'
#1500000
0'
#1510000
b1 6
1'
#1520000
0'
#1530000
b10 6
1'
#1540000
0'
#1550000
1,
b11 6
1'
#1560000
0'
#1570000
0,
b0 6
b1 4
1'
#1580000
0'
#1590000
b1 6
1'
#1600000
0'
#1610000
b10 6
1'
#1620000
0'
#1630000
1,
b11 6
1'
#1640000
0'
#1650000
0,
b0 6
b10 4
1'
#1660000
0'
b1 *
